{
	"@type": "siibra/feature/connectivitymatrix/v0.3",
	"modality": "AnatomoFunctionalConnectivity",
	"cohort": "adult pharmaco-resistant focal epilepsy patients",
	"description": "F-TRACT: a probabilistic atlas of anatomo-functional connectivity of the human brain - F-TRACT_P_01_v2307",
	"parcellation": {
		"@id": "minds/core/parcellationatlas/v1.0.0/94c1125b-b87e-45e4-901c-00daee7f2579-300"
	},
	"repository": {
		"@type": "siibra/repository/dataproxy/v1.0.0",
		"bucketname": "d-41db823e-7e1b-44c7-9c69-eaa26e226384",
		"folder": "MNI-JulichBrain-3.0"
	},
	"ebrains": {
		"minds/core/species/v1.0.0": "0ea4e6ba-2681-4f7d-9fa9-49b915caaac9",
		"openminds/Species": "97c070c6-8e1f-4ee8-9d28-18c7945921dd",
		"openminds/Dataset": "dc0750b4-1dd1-42d8-9e50-7f2fa97db085",
		"openminds/DatasetVersion": "41db823e-7e1b-44c7-9c69-eaa26e226384"
	},
	"decoder": {
		"@type": "siibra/decoder/csv",
		"delimiter": " ",
		"engine": "python",
		"header": null,
		"index_col": false,
		"skiprows": 8,
		"compression": "gzip"
	},
	"files_indexed_by": "feature",
	"files": {
		"P_01: amplitude__mad": "amplitude__mad.txt.gz",
		"P_01: amplitude__median": "amplitude__median.txt.gz",
		"P_01: dcm_axonal_delay__mad": "dcm_axonal_delay__mad.txt.gz",
		"P_01: dcm_axonal_delay__median": "dcm_axonal_delay__median.txt.gz",
		"P_01: dcm_excitatory_tc__mad": "dcm_excitatory_tc__mad.txt.gz",
		"P_01: dcm_excitatory_tc__median": "dcm_excitatory_tc__median.txt.gz",
		"P_01: dcm_inhibitory_tc__mad": "dcm_inhibitory_tc__mad.txt.gz",
		"P_01: dcm_inhibitory_tc__median": "dcm_inhibitory_tc__median.txt.gz",
		"P_01: duration__mad": "duration__mad.txt.gz",
		"P_01: duration__median": "duration__median.txt.gz",
		"P_01: integral__mad": "integral__mad.txt.gz",
		"P_01: integral__median": "integral__median.txt.gz",
		"P_01: latency_start__mad": "latency_start__mad.txt.gz",
		"P_01: latency_start__median": "latency_start__median.txt.gz",
		"P_01: N_implantations": "N_implantations.txt.gz",
		"P_01: N_stimulations": "N_stimulations.txt.gz",
		"P_01: onset_delay__mad": "onset_delay__mad.txt.gz",
		"P_01: onset_delay__median": "onset_delay__median.txt.gz",
		"P_01: peak_delay__mad": "peak_delay__mad.txt.gz",
		"P_01: peak_delay__median": "peak_delay__median.txt.gz",
		"P_01: probability": "probability.txt.gz",
		"P_01: slope__mad": "slope__mad.txt.gz",
		"P_01: slope__median": "slope__median.txt.gz",
		"P_01: speed__euclidian__dcm_axonal_delay__mad": "speed__euclidian__dcm_axonal_delay__mad.txt.gz",
		"P_01: speed__euclidian__dcm_axonal_delay__median": "speed__euclidian__dcm_axonal_delay__median.txt.gz",
		"P_01: speed__euclidian__latency_start__mad": "speed__euclidian__latency_start__mad.txt.gz",
		"P_01: speed__euclidian__latency_start__median": "speed__euclidian__latency_start__median.txt.gz",
		"P_01: speed__euclidian__onset_delay__mad": "speed__euclidian__onset_delay__mad.txt.gz",
		"P_01: speed__euclidian__onset_delay__median": "speed__euclidian__onset_delay__median.txt.gz",
		"P_01: speed__fibres__dcm_axonal_delay__mad": "speed__fibres__dcm_axonal_delay__mad.txt.gz",
		"P_01: speed__fibres__dcm_axonal_delay__median": "speed__fibres__dcm_axonal_delay__median.txt.gz",
		"P_01: speed__euclidian__peak_delay__mad": "speed__euclidian__peak_delay__mad.txt.gz",
		"P_01: speed__euclidian__peak_delay__median": "speed__euclidian__peak_delay__median.txt.gz",
		"P_01: speed__fibres__latency_start__mad": "speed__fibres__latency_start__mad.txt.gz",
		"P_01: speed__fibres__latency_start__median": "speed__fibres__latency_start__median.txt.gz",
		"P_01: speed__fibres__onset_delay__mad": "speed__fibres__onset_delay__mad.txt.gz",
		"P_01: speed__fibres__onset_delay__median": "speed__fibres__onset_delay__median.txt.gz",
		"P_01: speed__fibres__peak_delay__mad": "speed__fibres__peak_delay__mad.txt.gz",
		"P_01: speed__fibres__peak_delay__median": "speed__fibres__peak_delay__median.txt.gz"
	},
	"regions": [
		"Area 45 (IFG) left",
		"Area 45 (IFG) right",
		"Area 44 (IFG) left",
		"Area 44 (IFG) right",
		"Area Fo1 (OFC) left",
		"Area Fo1 (OFC) right",
		"Area Fo2 (OFC) left",
		"Area Fo2 (OFC) right",
		"Area Fo3 (OFC) left",
		"Area Fo3 (OFC) right",
		"Area hOc5 (LOC) left",
		"Area hOc5 (LOC) right",
		"Area hOc2 (V2, 18) left",
		"Area hOc2 (V2, 18) right",
		"Area hOc1 (V1, 17, CalcS) left",
		"Area hOc1 (V1, 17, CalcS) right",
		"Area hOc4v (LingG) left",
		"Area hOc4v (LingG) right",
		"Area hOc3v (LingG) left",
		"Area hOc3v (LingG) right",
		"Area TE 1.0 (HESCHL) left",
		"Area TE 1.0 (HESCHL) right",
		"Area TE 2.1 (STG) left",
		"Area TE 2.1 (STG) right",
		"Area TPJ (STG/SMG) left",
		"Area TPJ (STG/SMG) right",
		"Area TE 1.2 (HESCHL) left",
		"Area TE 1.2 (HESCHL) right",
		"Area TE 3 (STG) left",
		"Area TE 3 (STG) right",
		"Area TE 1.1 (HESCHL) left",
		"Area TE 1.1 (HESCHL) right",
		"Area TE 2.2 (STG) left",
		"Area TE 2.2 (STG) right",
		"Area 33 (ACC) left",
		"Area 33 (ACC) right",
		"Area s32 (sACC) left",
		"Area s32 (sACC) right",
		"Area p32 (pACC) left",
		"Area p32 (pACC) right",
		"Area Id2 (Insula) left",
		"Area Id2 (Insula) right",
		"Area Id3 (Insula) left",
		"Area Id3 (Insula) right",
		"CA2 (Hippocampus) left",
		"CA2 (Hippocampus) right",
		"CA3 (Hippocampus) left",
		"CA3 (Hippocampus) right",
		"Entorhinal Cortex left",
		"Entorhinal Cortex right",
		"DG (Hippocampus) left",
		"DG (Hippocampus) right",
		"CA1 (Hippocampus) left",
		"CA1 (Hippocampus) right",
		"HATA (Hippocampus) left",
		"HATA (Hippocampus) right",
		"Area OP4 (POperc) left",
		"Area OP4 (POperc) right",
		"Area OP1 (POperc) left",
		"Area OP1 (POperc) right",
		"Area OP2 (POperc) left",
		"Area OP2 (POperc) right",
		"Area OP3 (POperc) left",
		"Area OP3 (POperc) right",
		"Area FG2 (FusG) left",
		"Area FG2 (FusG) right",
		"Area FG1 (FusG) left",
		"Area FG1 (FusG) right",
		"Area PGp (IPL) left",
		"Area PGp (IPL) right",
		"Area PFt (IPL) left",
		"Area PFt (IPL) right",
		"Area PGa (IPL) left",
		"Area PGa (IPL) right",
		"Area PFop (IPL) left",
		"Area PFop (IPL) right",
		"Area PFm (IPL) left",
		"Area PFm (IPL) right",
		"Area PFcm (IPL) left",
		"Area PFcm (IPL) right",
		"Area Ig2 (Insula) left",
		"Area Ig2 (Insula) right",
		"Area Ig1 (Insula) left",
		"Area Ig1 (Insula) right",
		"Area Id1 (Insula) left",
		"Area Id1 (Insula) right",
		"Area hOc4lp (LOC) left",
		"Area hOc4lp (LOC) right",
		"Area hOc4la (LOC) left",
		"Area hOc4la (LOC) right",
		"Area hOc4d (Cuneus) left",
		"Area hOc4d (Cuneus) right",
		"Area hOc3d (Cuneus) left",
		"Area hOc3d (Cuneus) right",
		"Area 4p (PreCG) left",
		"Area 4p (PreCG) right",
		"Area 4a (PreCG) left",
		"Area 4a (PreCG) right",
		"Area 1 (PostCG) left",
		"Area 1 (PostCG) right",
		"Area 3a (PostCG) left",
		"Area 3a (PostCG) right",
		"Area 3b (PostCG) left",
		"Area 3b (PostCG) right",
		"Area hIP1 (IPS) left",
		"Area hIP1 (IPS) right",
		"Area hIP2 (IPS) left",
		"Area hIP2 (IPS) right",
		"Area 5L (SPL) left",
		"Area 5L (SPL) right",
		"Area 5M (SPL) left",
		"Area 5M (SPL) right",
		"Area 7PC (SPL) left",
		"Area 7PC (SPL) right",
		"Area hIP3 (IPS) left",
		"Area hIP3 (IPS) right",
		"Area 7A (SPL) left",
		"Area 7A (SPL) right",
		"Area 7M (SPL) left",
		"Area 7M (SPL) right",
		"Area 5Ci (SPL) left",
		"Area 5Ci (SPL) right",
		"Area Id7 (Insula) left",
		"Area Id7 (Insula) right",
		"Area s24 (sACC) left",
		"Area s24 (sACC) right",
		"Area 25 (sACC) left",
		"Area 25 (sACC) right",
		"SF (Amygdala) left",
		"SF (Amygdala) right",
		"LB (Amygdala) left",
		"LB (Amygdala) right",
		"Subiculum (Hippocampus) left",
		"Subiculum (Hippocampus) right",
		"Area PF (IPL) left",
		"Area PF (IPL) right",
		"Area 7P (SPL) left",
		"Area 7P (SPL) right",
		"Area Fp2 (FPole) left",
		"Area Fp2 (FPole) right",
		"Area Fp1 (FPole) left",
		"Area Fp1 (FPole) right",
		"Fastigial Nucleus (Cerebellum) left",
		"Fastigial Nucleus (Cerebellum) right",
		"VTM (Amygdala) left",
		"VTM (Amygdala) right",
		"Area p24ab (pACC) left",
		"Area p24ab (pACC) right",
		"Area p24c (pACC) left",
		"Area p24c (pACC) right",
		"MF (Amygdala) left",
		"MF (Amygdala) right",
		"IF (Amygdala) left",
		"IF (Amygdala) right",
		"Area FG4 (FusG) left",
		"Area FG4 (FusG) right",
		"Area FG3 (FusG) left",
		"Area FG3 (FusG) right",
		"Dorsal Dentate Nucleus (Cerebellum) left",
		"Dorsal Dentate Nucleus (Cerebellum) right",
		"Ventral Dentate Nucleus (Cerebellum) left",
		"Ventral Dentate Nucleus (Cerebellum) right",
		"Area TeI (STG) left",
		"Area TeI (STG) right",
		"Area TI (STG) left",
		"Area TI (STG) right",
		"Area IFS1 (IFS) left",
		"Area IFS1 (IFS) right",
		"Area IFS2 (IFS) left",
		"Area IFS2 (IFS) right",
		"Area IFS3 (IFS) left",
		"Area IFS3 (IFS) right",
		"Area IFS4 (IFS) left",
		"Area IFS4 (IFS) right",
		"Area IFJ1 (IFS,PreCS) left",
		"Area IFJ1 (IFS,PreCS) right",
		"Area IFJ2 (IFS,PreCS) left",
		"Area IFJ2 (IFS,PreCS) right",
		"Interposed Nucleus (Cerebellum) left",
		"Interposed Nucleus (Cerebellum) right",
		"Area 2 (PostCS) left",
		"Area 2 (PostCS) right",
		"Ch 4 (Basal Forebrain) left",
		"Ch 4 (Basal Forebrain) right",
		"Area STS1 (STS) left",
		"Area STS1 (STS) right",
		"Area STS2 (STS) left",
		"Area STS2 (STS) right",
		"Area Op8 (Frontal Operculum) left",
		"Area Op8 (Frontal Operculum) right",
		"Area Op9 (Frontal Operculum) left",
		"Area Op9 (Frontal Operculum) right",
		"Ch 123 (Basal Forebrain) left",
		"Ch 123 (Basal Forebrain) right",
		"Area 6d1 (PreCG) left",
		"Area 6d1 (PreCG) right",
		"Area 6d2 (PreCG) left",
		"Area 6d2 (PreCG) right",
		"Area 6d3 (SFS) left",
		"Area 6d3 (SFS) right",
		"CM (Amygdala) left",
		"CM (Amygdala) right",
		"Area hOc6 (POS) left",
		"Area hOc6 (POS) right",
		"Area hIP6 (IPS) left",
		"Area hIP6 (IPS) right",
		"Area hIP8 (IPS) left",
		"Area hIP8 (IPS) right",
		"Area hIP4 (IPS) left",
		"Area hIP4 (IPS) right",
		"Area hIP5 (IPS) left",
		"Area hIP5 (IPS) right",
		"Area hIP7 (IPS) left",
		"Area hIP7 (IPS) right",
		"Area hPO1 (POS) left",
		"Area hPO1 (POS) right",
		"Area 6mp (SMA, mesial SFG) left",
		"Area 6mp (SMA, mesial SFG) right",
		"Area 6ma (preSMA, mesial SFG) left",
		"Area 6ma (preSMA, mesial SFG) right",
		"HC-Transsubiculum (Hippocampus) left",
		"HC-Transsubiculum (Hippocampus) right",
		"Tuberculum (Basal Forebrain) left",
		"Tuberculum (Basal Forebrain) right",
		"Terminal islands (Basal Forebrain) left",
		"Terminal islands (Basal Forebrain) right",
		"Area Fo4 (OFC) left",
		"Area Fo4 (OFC) right",
		"Area Fo5 (OFC) left",
		"Area Fo5 (OFC) right",
		"Area Fo6 (OFC) left",
		"Area Fo6 (OFC) right",
		"Area Fo7 (OFC) left",
		"Area Fo7 (OFC) right",
		"Area 8d1 (SFG) left",
		"Area 8d1 (SFG) right",
		"Area 8d2 (SFG) left",
		"Area 8d2 (SFG) right",
		"Area 8v2 (MFG) left",
		"Area 8v2 (MFG) right",
		"Area 8v1 (MFG) left",
		"Area 8v1 (MFG) right",
		"Area Ig3 (Insula) left",
		"Area Ig3 (Insula) right",
		"Area Id4 (Insula) left",
		"Area Id4 (Insula) right",
		"Area Id5 (Insula) left",
		"Area Id5 (Insula) right",
		"Area Ia1 (Insula) left",
		"Area Ia1 (Insula) right",
		"Area Id6 (Insula) left",
		"Area Id6 (Insula) right",
		"Area SFS1 (SFS) left",
		"Area SFS1 (SFS) right",
		"Area SFS2 (SFS) left",
		"Area SFS2 (SFS) right",
		"Area MFG1 (MFG) left",
		"Area MFG1 (MFG) right",
		"Area MFG2 (MFG) left",
		"Area MFG2 (MFG) right",
		"Area Op5 (Frontal Operculum) left",
		"Area Op5 (Frontal Operculum) right",
		"Area Op6 (Frontal Operculum) left",
		"Area Op6 (Frontal Operculum) right",
		"Area Op7 (Frontal Operculum) left",
		"Area Op7 (Frontal Operculum) right",
		"Area Ph1 (PhG) left",
		"Area Ph1 (PhG) right",
		"Area Ph2 (PhG) left",
		"Area Ph2 (PhG) right",
		"Area Ph3 (PhG) left",
		"Area Ph3 (PhG) right",
		"Area CoS1 (CoS) left",
		"Area CoS1 (CoS) right",
		"Medial Accumbens, ventral Striatum left",
		"Medial Accumbens, ventral Striatum right",
		"Fundus of Caudate Nucleus, ventral Striatum left",
		"Fundus of Caudate Nucleus, ventral Striatum right",
		"Fundus of Putamen, Ventral Striatum left",
		"Fundus of Putamen, Ventral Striatum right",
		"Lateral Accumbens, ventral Striatum left",
		"Lateral Accumbens, ventral Striatum right",
		"VP, ventral Pallidum left",
		"VP, ventral Pallidum right",
		"CGL (Metathalamus) left",
		"CGL (Metathalamus) right",
		"CGM (Metathalamus) left",
		"CGM (Metathalamus) right",
		"STN (Subthalamus) left",
		"STN (Subthalamus) right",
		"Area Id9 (Insula) left",
		"Area Id9 (Insula) right",
		"Area Ia3 (Insula) left",
		"Area Ia3 (Insula) right",
		"Area Ia2 (Insula) left",
		"Area Ia2 (Insula) right",
		"Area Id8 (Insula) left",
		"Area Id8 (Insula) right",
		"Area Id10 (Insula) left",
		"Area Id10 (Insula) right",
		"BST (Bed Nucleus) left",
		"BST (Bed Nucleus) right",
		"Frontal-I (GapMap) left",
		"Frontal-I (GapMap) right",
		"Frontal-II (GapMap) left",
		"Frontal-II (GapMap) right",
		"Temporal-to-Parietal (GapMap) left",
		"Temporal-to-Parietal (GapMap) right",
		"Frontal-to-Occipital (GapMap) left",
		"Frontal-to-Occipital (GapMap) right",
		"Frontal-to-Temporal-I (GapMap) left",
		"Frontal-to-Temporal-I (GapMap) right",
		"Frontal-to-Temporal-II (GapMap) left",
		"Frontal-to-Temporal-II (GapMap) right"
	]
}