{
	"@id": "juelich/iav/atlas/v1.0.0/6",
	"@type": "siibra/parcellation/v0.0.1",
	"name": "Superficial fibre bundles",
	"shortName": "Superficial fibre bundles",
	"description": "This data contains the maximum probability map of superficial white matter fibre bundles, in the MNI ICBM152 reference brain. These bundles were identified using a hybrid approach, incorporating anatomical information (from cortical regions of interest) and fibre shape (fibre clustering), from the tractography datasets of 78 subjects in the Neurospin\u2019s ARCHI database. The maximum probability corresponds to the voxels with the highest number of putative fibres going through.",
	"modality": "fibre architecture",
	"species": "homo sapiens",
	"regions": [
		{
			"name": "Left Hemisphere",
			"children": [
				{
					"name": "Caudal Middle Frontal - Precuneus",
					"children": [
						{
							"name": "lh_CAC-PrCu_0"
						}
					]
				},
				{
					"name": "Caudal Middle Frontal \u2013 Pars Opercularis",
					"children": [
						{
							"name": "lh_CMF-Op_0"
						}
					]
				},
				{
					"name": "Caudal Middle Frontal - Poscentral",
					"children": [
						{
							"name": "lh_CMF-PoC_0"
						}
					]
				},
				{
					"name": "Caudal Middle Frontal - Precentral",
					"children": [
						{
							"name": "lh_CMF-PrC_0"
						},
						{
							"name": "lh_CMF-PrC_1"
						}
					]
				},
				{
					"name": "Caudal Middle Frontal \u2013 Rostral Middle Frontal",
					"children": [
						{
							"name": "lh_CMF-RMF_0"
						}
					]
				},
				{
					"name": "Caudal Middle Frontal \u2013 Superior Frontal",
					"children": [
						{
							"name": "lh_CMF-SF_0"
						}
					]
				},
				{
					"name": "Fusiform \u2013 Lateral Occipital",
					"children": [
						{
							"name": "lh_Fu-LO_0"
						}
					]
				},
				{
					"name": "Isthmus Cingulate - Precuneus",
					"children": [
						{
							"name": "lh_IC-PrCu_0"
						}
					]
				},
				{
					"name": "Inferior Parietal \u2013 Inferior Temporal",
					"children": [
						{
							"name": "lh_IP-IT_0"
						}
					]
				},
				{
					"name": "Inferior Parietal \u2013 Lateral Occipital",
					"children": [
						{
							"name": "lh_IP-LO_1"
						}
					]
				},
				{
					"name": "Inferior Parietal \u2013 Middle Temporal\t",
					"children": [
						{
							"name": "lh_IP-MT_0"
						}
					]
				},
				{
					"name": "Inferior Parietal - Supramarginal",
					"children": [
						{
							"name": "lh_IP-SM_0"
						}
					]
				},
				{
					"name": "Inferior Pariertal \u2013 Superior Parietal",
					"children": [
						{
							"name": "lh_IP-SP_0"
						},
						{
							"name": "lh_IP-SP_1"
						}
					]
				},
				{
					"name": "Inferior Temporal \u2013 Middle Temporal",
					"children": [
						{
							"name": "lh_IT-MT_0"
						}
					]
				},
				{
					"name": "Lateral Orbitofrontal \u2013 Pars Orbitalis",
					"children": [
						{
							"name": "lh_LOF-Or_0"
						}
					]
				},
				{
					"name": "Lateral Orbitofrontal \u2013 Rostral Middle Frontal",
					"children": [
						{
							"name": "lh_LOF-RMF_0"
						},
						{
							"name": "lh_LOF-RMF_1"
						}
					]
				},
				{
					"name": "Lateral Orbitofrontal \u2013 Superior Temporal",
					"children": [
						{
							"name": "lh_LOF-ST_0"
						}
					]
				},
				{
					"name": "Middle Orbitofrontal \u2013 Superior Temporal",
					"children": [
						{
							"name": "lh_MOF-ST_0"
						}
					]
				},
				{
					"name": "Middle Temporal - Supramarginal",
					"children": [
						{
							"name": "lh_MT-SM_0"
						}
					]
				},
				{
					"name": "Middle Temporal \u2013 Superior Temporal",
					"children": [
						{
							"name": "lh_MT-ST_0"
						}
					]
				},
				{
					"name": "Pars Opercularis - Insula",
					"children": [
						{
							"name": "lh_Op-Ins_0"
						}
					]
				},
				{
					"name": "Pars Opercularis - Precentral`",
					"children": [
						{
							"name": "lh_Op-PrC_0"
						}
					]
				},
				{
					"name": "Pars Opercularis \u2013 Superior Frontal",
					"children": [
						{
							"name": "lh_Op-SF_0"
						}
					]
				},
				{
					"name": "Pars Orbitalis - Insula",
					"children": [
						{
							"name": "lh_Or-Ins_0"
						}
					]
				},
				{
					"name": "Postcentral - Insula",
					"children": [
						{
							"name": "lh_PoC-Ins_0"
						}
					]
				},
				{
					"name": "Poscentral - Precuneus",
					"children": [
						{
							"name": "lh_PoCi-PrCu_0"
						},
						{
							"name": "lh_PoCi-PrCu_1"
						}
					]
				},
				{
					"name": "Posterior Cingulate \u2013 Rostral Anterior Cingulate",
					"children": [
						{
							"name": "lh_PoCi-RAC_0"
						}
					]
				},
				{
					"name": "Posterior Cingulate \u2013 Superior Frontal",
					"children": [
						{
							"name": "lh_PoCi-SF_0"
						}
					]
				},
				{
					"name": "Poscentral - Precentral",
					"children": [
						{
							"name": "lh_PoC-PrC_0"
						},
						{
							"name": "lh_PoC-PrC_1"
						},
						{
							"name": "lh_PoC-PrC_2"
						},
						{
							"name": "lh_PoC-PrC_3"
						}
					]
				},
				{
					"name": "Poscentral - Supramarginal",
					"children": [
						{
							"name": "lh_PoC-SM_0"
						},
						{
							"name": "lh_PoC-SM_1"
						}
					]
				},
				{
					"name": "Precentral - Insula",
					"children": [
						{
							"name": "lh_PrC-Ins_0"
						}
					]
				},
				{
					"name": "Precentral \u2013 Superior Frontal",
					"children": [
						{
							"name": "lh_PrC-SF_0"
						}
					]
				},
				{
					"name": "Precentral - Supramarginal",
					"children": [
						{
							"name": "lh_PrC-SM_0"
						}
					]
				},
				{
					"name": "Rostral Anterior Cingulate \u2013 Superior Frontal",
					"children": [
						{
							"name": "lh_RAC-SF_1"
						}
					]
				},
				{
					"name": "Rostral Middle Frontal \u2013 Superior Frontal",
					"children": [
						{
							"name": "lh_RMF-SF_0"
						},
						{
							"name": "lh_RMF-SF_1"
						}
					]
				},
				{
					"name": "Supramarginal - Insula",
					"children": [
						{
							"name": "lh_SM-Ins_0"
						}
					]
				},
				{
					"name": "Superior Parietal - Supramarginal",
					"children": [
						{
							"name": "lh_SP-SM_0"
						}
					]
				},
				{
					"name": "Superior Temporal - Insula",
					"children": [
						{
							"name": "lh_ST-Ins_0"
						}
					]
				},
				{
					"name": "Superior Temporal \u2013 Transverse Temporal",
					"children": [
						{
							"name": "lh_ST-TT_0"
						}
					]
				},
				{
					"name": "Pars Triangularis - Insula",
					"children": [
						{
							"name": "lh_Tr-Ins_0"
						}
					]
				},
				{
					"name": "Pars Triangularis \u2013 Superior Frontal",
					"children": [
						{
							"name": "lh_Tr-SF_0"
						}
					]
				}
			]
		},
		{
			"name": "Right Hemisphere",
			"children": [
				{
					"name": "Caudal Middle Frontal \u2013 Posterior Cingulate",
					"children": [
						{
							"name": "rh_CAC-PoCi_0"
						}
					]
				},
				{
					"name": "Caudal Middle Frontal - Precuneus",
					"children": [
						{
							"name": "rh_CAC-PrCu_0"
						}
					]
				},
				{
					"name": "Caudal Middle Frontal - Precentral",
					"children": [
						{
							"name": "rh_CMF-PrC_0"
						},
						{
							"name": "rh_CMF-PrC_1"
						}
					]
				},
				{
					"name": "Caudal Middle Frontal \u2013 Rostral Middle Frontal",
					"children": [
						{
							"name": "rh_CMF-RMF_0"
						}
					]
				},
				{
					"name": "Caudal Middle Frontal \u2013 Superior Frontal",
					"children": [
						{
							"name": "rh_CMF-SF_0"
						}
					]
				},
				{
					"name": "Caudal Middle Frontal \u2013 Superior Frontal\t\t",
					"children": [
						{
							"name": "rh_CMF-SF_1"
						}
					]
				},
				{
					"name": "Cuneus - Lingual",
					"children": [
						{
							"name": "rh_Cu-Li_0"
						}
					]
				},
				{
					"name": "Fusiform \u2013 Lateral Occipital",
					"children": [
						{
							"name": "rh_Fu-LO_1"
						}
					]
				},
				{
					"name": "Isthmus Cingulate - Precuneus",
					"children": [
						{
							"name": "rh_IC-PrCu_0"
						}
					]
				},
				{
					"name": "Inferior Parietal \u2013 Inferior Temporal ",
					"children": [
						{
							"name": "rh_IP-IT_0"
						}
					]
				},
				{
					"name": "Inferior Parietal \u2013 Lateral Occipital",
					"children": [
						{
							"name": "rh_IP-LO_0"
						}
					]
				},
				{
					"name": "Inferior Parietal \u2013 Middle Temporal",
					"children": [
						{
							"name": "rh_IP-MT_0"
						}
					]
				},
				{
					"name": "Inferior Parietal - Supramarginal",
					"children": [
						{
							"name": "rh_IP-SM_0"
						}
					]
				},
				{
					"name": "Inferior Parietal \u2013 Superior Parietal",
					"children": [
						{
							"name": "rh_IP-SP_0"
						}
					]
				},
				{
					"name": "Inferior Temporal \u2013 Middle Temporal",
					"children": [
						{
							"name": "rh_IT-MT_1"
						},
						{
							"name": "rh_IT-MT_2"
						}
					]
				},
				{
					"name": "Lateral Orbitofrontal \u2013 Middle Orbitofrontal",
					"children": [
						{
							"name": "rh_LOF-MOF_0"
						}
					]
				},
				{
					"name": "Lateral Orbitofrontal \u2013 Rostral Middle Frontal",
					"children": [
						{
							"name": "rh_LOF-RMF_0"
						},
						{
							"name": "rh_LOF-RMF_1"
						}
					]
				},
				{
					"name": "Lateral Orbitofrontal \u2013 Superior Temporal",
					"children": [
						{
							"name": "rh_LOF-ST_0"
						}
					]
				},
				{
					"name": "Lateral Orbitofrontal \u2013 Superior Parietal",
					"children": [
						{
							"name": "rh_LO-SP_0"
						}
					]
				},
				{
					"name": "Middle Orbitofrontal \u2013 Superior Temporal",
					"children": [
						{
							"name": "rh_MOF-ST_0"
						}
					]
				},
				{
					"name": "Middle Temporal - Supramarginal",
					"children": [
						{
							"name": "rh_MT-SM_0"
						}
					]
				},
				{
					"name": "Middle Temporal \u2013 Superior Temporal",
					"children": [
						{
							"name": "rh_MT-ST_0"
						}
					]
				},
				{
					"name": "Pars Opercularis - Insula",
					"children": [
						{
							"name": "rh_Op-Ins_0"
						}
					]
				},
				{
					"name": "Pars Opercularis - Precentral",
					"children": [
						{
							"name": "rh_Op-PrC_0"
						}
					]
				},
				{
					"name": "Pars Opercularis \u2013 Superior Frontal",
					"children": [
						{
							"name": "rh_Op-SF_0"
						}
					]
				},
				{
					"name": "Pars Opercularis \u2013 Pars Triangularis",
					"children": [
						{
							"name": "rh_Op-Tr_0"
						}
					]
				},
				{
					"name": "Pars Orbitalis - Insula",
					"children": [
						{
							"name": "rh_Or-Ins_0"
						}
					]
				},
				{
					"name": "Posterior Cingulate - Precuneus",
					"children": [
						{
							"name": "rh_PoCi-PrCu_1"
						},
						{
							"name": "rh_PoCi-PrCu_2"
						}
					]
				},
				{
					"name": "Posterior Cingulate \u2013 Rostral Anterior Cingulate",
					"children": [
						{
							"name": "rh_PoCi-RAC_0"
						}
					]
				},
				{
					"name": "Poscentral - Precentral",
					"children": [
						{
							"name": "rh_PoC-PrC_0"
						},
						{
							"name": "rh_PoC-PrC_1"
						},
						{
							"name": "rh_PoC-PrC_2"
						}
					]
				},
				{
					"name": "Postcentral - Supramarginal",
					"children": [
						{
							"name": "rh_PoC-SM_0"
						}
					]
				},
				{
					"name": "Postcentral \u2013 Superior Parietal",
					"children": [
						{
							"name": "rh_PoC-SP_0"
						},
						{
							"name": "rh_PoC-SP_1"
						}
					]
				},
				{
					"name": "Precentral - Insula",
					"children": [
						{
							"name": "rh_PrC-Ins_0"
						}
					]
				},
				{
					"name": "Precentral - Supramarginal\t",
					"children": [
						{
							"name": "rh_PrC-SM_0"
						}
					]
				},
				{
					"name": "Precentral \u2013 Superior Parietal",
					"children": [
						{
							"name": "rh_PrC-SP_0"
						}
					]
				},
				{
					"name": "Rostral Anterior Cingulate",
					"children": [
						{
							"name": "rh_RAC-SF_0"
						}
					]
				},
				{
					"name": "Rostral Middle Frontal \u2013 Superior Frontal",
					"children": [
						{
							"name": "rh_RMF-SF_0"
						},
						{
							"name": "rh_RMF-SF_1"
						}
					]
				},
				{
					"name": "Supramarginal - Insula",
					"children": [
						{
							"name": "rh_SM-Ins_0"
						}
					]
				},
				{
					"name": "Superior Parietal - Supramarginal",
					"children": [
						{
							"name": "rh_SP-SM_0"
						}
					]
				},
				{
					"name": "Superior Temporal \u2013 Transverse Temporal",
					"children": [
						{
							"name": "rh_ST-TT_0"
						}
					]
				},
				{
					"name": "Pars Triangularis - Insula",
					"children": [
						{
							"name": "rh_Tr-Ins_0"
						}
					]
				},
				{
					"name": "Pars Triangularis \u2013 Superior Frontal",
					"children": [
						{
							"name": "rh_Tr-SF_0"
						}
					]
				}
			]
		}
	],
	"ebrains": {
		"openminds/Species": "97c070c6-8e1f-4ee8-9d28-18c7945921dd",
		"openminds/DatasetVersion": "06246ac0-af1c-4277-a885-8865c4ff4bf3"
	},
	"publications": [
		{
			"citation": "Guevara, P., Duclap, D., Poupon, C., Marrakchi-Kacem, L., Fillard, P., Le Bihan, D., Leboyer, M., Houenou, J., Mangin, J.- F (2012). Automatic fiber bundle segmentation in massive tractography datasets using a multi-subject bundle atlas. NeuroImage, 61(4),1083-99.",
			"url": "https://doi.org/10.1016/j.neuroimage.2012.02.071"
		}
	]
}
