{
	"@type": "siibra/atlases/parcellation_map/v0.1",
	"parcellation_id": "minds/core/parcellationatlas/v1.0.0/63b5794f-79a4-4464-8dc1-b32e170f3d16",
	"space_id": "minds/core/referencespace/v1.0.0/dafcffc5-4826-4bf1-8ff6-46b8a31ff8e2",
	"maptype": "statistical",
	"sparsemap": true,
	"attributes": [
		{
			"@type": "siibra/attr/desc/id/v0.1",
			"value": "8941545a-c757-fb97-c826-7cb3fdf10142"
		},
		{
			"@type": "siibra/attr/desc/name/v0.1",
			"value": "DiFuMo Atlas (512 dimensions) on MNI 152 ICBM 2009c Nonlinear Asymmetric - statistical - 256 regions"
		},
		{
			"@type": "siibra/attr/desc/speciesspec/v0.1",
			"value": "homo sapiens"
		},
		{
			"@type": "siibra/attr/data/image/v0.1",
			"space_id": "minds/core/referencespace/v1.0.0/dafcffc5-4826-4bf1-8ff6-46b8a31ff8e2",
			"format": "nii",
			"url": "https://object.cscs.ch/v1/AUTH_4791e0a3b3de43e2840fe46d9dc2b334/ext-d000017_DiFuMoAtlases_pub/512/maps.nii.gz",
			"mapping": {
				"Component 1: Superior occipital sulcus inferior - left hemisphere": {
					"subspace": [
						":",
						":",
						":",
						0
					],
					"range": []
				},
				"Component 2: Superior occipital gyrus ": {
					"subspace": [
						":",
						":",
						":",
						1
					],
					"range": []
				},
				"Component 3: Insula antero-inferior": {
					"subspace": [
						":",
						":",
						":",
						2
					],
					"range": []
				},
				"Component 4: Middle frontal gyrus middle - right hemisphere": {
					"subspace": [
						":",
						":",
						":",
						3
					],
					"range": []
				},
				"Component 5: Calcarine cortex posterior - left hemisphere": {
					"subspace": [
						":",
						":",
						":",
						4
					],
					"range": []
				},
				"Component 6: Lateral fissure posterior ramus - right hemisphere": {
					"subspace": [
						":",
						":",
						":",
						5
					],
					"range": []
				},
				"Component 7: Superior occipital gyrus superior - left hemisphere": {
					"subspace": [
						":",
						":",
						":",
						6
					],
					"range": []
				},
				"Component 8: Angular gyrus inferior - left hemisphere": {
					"subspace": [
						":",
						":",
						":",
						7
					],
					"range": []
				},
				"Component 9: Calcarine sulcus anterior - left hemisphere": {
					"subspace": [
						":",
						":",
						":",
						8
					],
					"range": []
				},
				"Component 10: Frontal pole inferior - right hemisphere": {
					"subspace": [
						":",
						":",
						":",
						9
					],
					"range": []
				},
				"Component 11: Midbrain superior": {
					"subspace": [
						":",
						":",
						":",
						10
					],
					"range": []
				},
				"Component 12: Occipitotemporal gyrus mid-posterior - right hemisphere": {
					"subspace": [
						":",
						":",
						":",
						11
					],
					"range": []
				},
				"Component 13: Insula postero-inferior medial": {
					"subspace": [
						":",
						":",
						":",
						12
					],
					"range": []
				},
				"Component 14: Cerebellum VI - right hemisphere": {
					"subspace": [
						":",
						":",
						":",
						13
					],
					"range": []
				},
				"Component 15: Fusiform gyrus anterior - left hemisphere": {
					"subspace": [
						":",
						":",
						":",
						14
					],
					"range": []
				},
				"Component 16: Cerebellum Crus I anterior - right hemisphere": {
					"subspace": [
						":",
						":",
						":",
						15
					],
					"range": []
				},
				"Component 17: Supramarginal gyrus antero-superior - left hemisphere": {
					"subspace": [
						":",
						":",
						":",
						16
					],
					"range": []
				},
				"Component 18: Angular sulcus superior - left hemisphere": {
					"subspace": [
						":",
						":",
						":",
						17
					],
					"range": []
				},
				"Component 19: Paracingulate sulcus - left hemisphere": {
					"subspace": [
						":",
						":",
						":",
						18
					],
					"range": []
				},
				"Component 20: Superior frontal gyrus superior": {
					"subspace": [
						":",
						":",
						":",
						19
					],
					"range": []
				},
				"Component 21: Pars triangularis - left hemisphere": {
					"subspace": [
						":",
						":",
						":",
						20
					],
					"range": []
				},
				"Component 22: Superior longitudinal fasciculus II - left hemisphere": {
					"subspace": [
						":",
						":",
						":",
						21
					],
					"range": []
				},
				"Component 23: Corona radiata antero-superior": {
					"subspace": [
						":",
						":",
						":",
						22
					],
					"range": []
				},
				"Component 24: Dorsomedial prefrontal cortex antero-superior - left hemisphere": {
					"subspace": [
						":",
						":",
						":",
						23
					],
					"range": []
				},
				"Component 25: Superior longitudinal fasciculus III anterior - left hemisphere": {
					"subspace": [
						":",
						":",
						":",
						24
					],
					"range": []
				},
				"Component 26: Cuneus antero-inferior": {
					"subspace": [
						":",
						":",
						":",
						25
					],
					"range": []
				},
				"Component 27: Anterior vertical ramus of the lateral fissure - left hemisphere": {
					"subspace": [
						":",
						":",
						":",
						26
					],
					"range": []
				},
				"Component 28: Corpus callosum isthmus anterior": {
					"subspace": [
						":",
						":",
						":",
						27
					],
					"range": []
				},
				"Component 29: Internal capsule posterior limb - right hemisphere": {
					"subspace": [
						":",
						":",
						":",
						28
					],
					"range": []
				},
				"Component 30: Cingulate gyrus middle inferior": {
					"subspace": [
						":",
						":",
						":",
						29
					],
					"range": []
				},
				"Component 31: Caudate - right hemisphere": {
					"subspace": [
						":",
						":",
						":",
						30
					],
					"range": []
				},
				"Component 32: Superior frontal sulcus anterior - right hemisphere": {
					"subspace": [
						":",
						":",
						":",
						31
					],
					"range": []
				},
				"Component 33: Pars orbitalis - right hemisphere": {
					"subspace": [
						":",
						":",
						":",
						32
					],
					"range": []
				},
				"Component 34: Cerebellum VIIb": {
					"subspace": [
						":",
						":",
						":",
						33
					],
					"range": []
				},
				"Component 35: Intraparietal sulcus anterior - left hemisphere": {
					"subspace": [
						":",
						":",
						":",
						34
					],
					"range": []
				},
				"Component 36: Superior longitudinal fasciculus I posterior - right hemisphere": {
					"subspace": [
						":",
						":",
						":",
						35
					],
					"range": []
				},
				"Component 37: Superior longitudinal fasciculus II middle - right hemisphere": {
					"subspace": [
						":",
						":",
						":",
						36
					],
					"range": []
				},
				"Component 38: Angular gyrus postero-inferior - right hemisphere": {
					"subspace": [
						":",
						":",
						":",
						37
					],
					"range": []
				},
				"Component 39: Cerebrospinal fluid (between middle frontal gyrus and skull)": {
					"subspace": [
						":",
						":",
						":",
						38
					],
					"range": []
				},
				"Component 40: Cerebellum III anterior": {
					"subspace": [
						":",
						":",
						":",
						39
					],
					"range": []
				},
				"Component 41: Central sulcus middle - right hemisphere": {
					"subspace": [
						":",
						":",
						":",
						40
					],
					"range": []
				},
				"Component 42: Cerebrospinal fluid (between interhemispheric fissure and superior frontal gyrus superio )": {
					"subspace": [
						":",
						":",
						":",
						41
					],
					"range": []
				},
				"Component 43: Superior frontal gyrus superior - right hemisphere": {
					"subspace": [
						":",
						":",
						":",
						42
					],
					"range": []
				},
				"Component 44: Frontal pole superior - right hemisphere": {
					"subspace": [
						":",
						":",
						":",
						43
					],
					"range": []
				},
				"Component 45: Postcentral sulcus - left hemisphere": {
					"subspace": [
						":",
						":",
						":",
						44
					],
					"range": []
				},
				"Component 46: Frontomarginal gyrus": {
					"subspace": [
						":",
						":",
						":",
						45
					],
					"range": []
				},
				"Component 47: Paracingulate sulcus posterior - right hemisphere": {
					"subspace": [
						":",
						":",
						":",
						46
					],
					"range": []
				},
				"Component 48: Middle frontal gyrus mid-anterior - left hemisphere": {
					"subspace": [
						":",
						":",
						":",
						47
					],
					"range": []
				},
				"Component 49: Middle frontal gyrus posterior lateral - right hemisphere": {
					"subspace": [
						":",
						":",
						":",
						48
					],
					"range": []
				},
				"Component 50: Intraparietal sulcus superior - left hemisphere": {
					"subspace": [
						":",
						":",
						":",
						49
					],
					"range": []
				},
				"Component 51: Ventromedial prefrontal cortex": {
					"subspace": [
						":",
						":",
						":",
						50
					],
					"range": []
				},
				"Component 52: Lingual gyrus posterior": {
					"subspace": [
						":",
						":",
						":",
						51
					],
					"range": []
				},
				"Component 53: Insula antero-superior - right hemisphere": {
					"subspace": [
						":",
						":",
						":",
						52
					],
					"range": []
				},
				"Component 54: Caudate superior": {
					"subspace": [
						":",
						":",
						":",
						53
					],
					"range": []
				},
				"Component 55: Parieto-occipital sulcus mid-posterior": {
					"subspace": [
						":",
						":",
						":",
						54
					],
					"range": []
				},
				"Component 56: Globus pallidus anterior": {
					"subspace": [
						":",
						":",
						":",
						55
					],
					"range": []
				},
				"Component 57: Superior longitudinal fasciculus I anterior - left hemisphere": {
					"subspace": [
						":",
						":",
						":",
						56
					],
					"range": []
				},
				"Component 58: Superior longitudinal fasciculus I anterior - right hemisphere": {
					"subspace": [
						":",
						":",
						":",
						57
					],
					"range": []
				},
				"Component 59: Precentral sulcus mid-inferior - left hemisphere": {
					"subspace": [
						":",
						":",
						":",
						58
					],
					"range": []
				},
				"Component 60: Cerebellum VI superior medial": {
					"subspace": [
						":",
						":",
						":",
						59
					],
					"range": []
				},
				"Component 61: Postcentral sulcus inferior - right hemisphere": {
					"subspace": [
						":",
						":",
						":",
						60
					],
					"range": []
				},
				"Component 62: Cuneus middle posterior - right hemisphere": {
					"subspace": [
						":",
						":",
						":",
						61
					],
					"range": []
				},
				"Component 63: Cerebrospinal fluid (between middle frontal gyrus superior and skull LH)": {
					"subspace": [
						":",
						":",
						":",
						62
					],
					"range": []
				},
				"Component 64: Paracingulate gyrus posterior - left hemisphere": {
					"subspace": [
						":",
						":",
						":",
						63
					],
					"range": []
				},
				"Component 65: Precentral gyrus mid-superior ": {
					"subspace": [
						":",
						":",
						":",
						64
					],
					"range": []
				},
				"Component 66: Superior temporal gyrus mid-anterior - left hemisphere": {
					"subspace": [
						":",
						":",
						":",
						65
					],
					"range": []
				},
				"Component 67: Fusiform gyrus anterior": {
					"subspace": [
						":",
						":",
						":",
						66
					],
					"range": []
				},
				"Component 68: Superior frontal gyrus medial anterior": {
					"subspace": [
						":",
						":",
						":",
						67
					],
					"range": []
				},
				"Component 69: Superior frontal gyrus mid-posterior ": {
					"subspace": [
						":",
						":",
						":",
						68
					],
					"range": []
				},
				"Component 70: Cerebellum IX": {
					"subspace": [
						":",
						":",
						":",
						69
					],
					"range": []
				},
				"Component 71: Thalamus posterior": {
					"subspace": [
						":",
						":",
						":",
						70
					],
					"range": []
				},
				"Component 72: Globus pallidus - right hemisphere": {
					"subspace": [
						":",
						":",
						":",
						71
					],
					"range": []
				},
				"Component 73: Postcentral sulcus - right hemisphere": {
					"subspace": [
						":",
						":",
						":",
						72
					],
					"range": []
				},
				"Component 74: Thalamus superior": {
					"subspace": [
						":",
						":",
						":",
						73
					],
					"range": []
				},
				"Component 75: Superior occipital sulcus superior - left hemisphere": {
					"subspace": [
						":",
						":",
						":",
						74
					],
					"range": []
				},
				"Component 76: Supramarginal gyrus posterior - left hemisphere": {
					"subspace": [
						":",
						":",
						":",
						75
					],
					"range": []
				},
				"Component 77: Gyrus rectus": {
					"subspace": [
						":",
						":",
						":",
						76
					],
					"range": []
				},
				"Component 78: Anterior occipital sulcus - right hemisphere": {
					"subspace": [
						":",
						":",
						":",
						77
					],
					"range": []
				},
				"Component 79: Lateral fissure anterior": {
					"subspace": [
						":",
						":",
						":",
						78
					],
					"range": []
				},
				"Component 80: Corona radiata posterior - left hemisphere": {
					"subspace": [
						":",
						":",
						":",
						79
					],
					"range": []
				},
				"Component 81: Cerebellum V anterior": {
					"subspace": [
						":",
						":",
						":",
						80
					],
					"range": []
				},
				"Component 82: Parieto-occipital sulcus mid-anterior": {
					"subspace": [
						":",
						":",
						":",
						81
					],
					"range": []
				},
				"Component 83: Hippocampus anterior": {
					"subspace": [
						":",
						":",
						":",
						82
					],
					"range": []
				},
				"Component 84: Superior frontal gyrus mid-anterior - left hemisphere": {
					"subspace": [
						":",
						":",
						":",
						83
					],
					"range": []
				},
				"Component 85: Cerebellum Crus II anterior - left hemisphere": {
					"subspace": [
						":",
						":",
						":",
						84
					],
					"range": []
				},
				"Component 86: Intraparietal sulcus middle - right hemisphere": {
					"subspace": [
						":",
						":",
						":",
						85
					],
					"range": []
				},
				"Component 87: Parieto-occipital sulcus posterior lateral": {
					"subspace": [
						":",
						":",
						":",
						86
					],
					"range": []
				},
				"Component 88: Occipital pole - left hemisphere": {
					"subspace": [
						":",
						":",
						":",
						87
					],
					"range": []
				},
				"Component 89: Corticospinal tract superior": {
					"subspace": [
						":",
						":",
						":",
						88
					],
					"range": []
				},
				"Component 90: Cingulate gyrus middle superior": {
					"subspace": [
						":",
						":",
						":",
						89
					],
					"range": []
				},
				"Component 91: Parieto-occipital sulcus anterior": {
					"subspace": [
						":",
						":",
						":",
						90
					],
					"range": []
				},
				"Component 92: Cererbrospinal fluid (between callosomarginal sulcus and skull LH)": {
					"subspace": [
						":",
						":",
						":",
						91
					],
					"range": []
				},
				"Component 93: Occipitotemporal gyrus posterior - right hemisphere": {
					"subspace": [
						":",
						":",
						":",
						92
					],
					"range": []
				},
				"Component 94: Insula postero-superior lateral - left hemisphere": {
					"subspace": [
						":",
						":",
						":",
						93
					],
					"range": []
				},
				"Component 95: Superior frontal gyrus posterior - left hemisphere": {
					"subspace": [
						":",
						":",
						":",
						94
					],
					"range": []
				},
				"Component 96: Inferior frontal sulcus middle - right hemisphere": {
					"subspace": [
						":",
						":",
						":",
						95
					],
					"range": []
				},
				"Component 97: Postcentral gyrus middle - left hemisphere": {
					"subspace": [
						":",
						":",
						":",
						96
					],
					"range": []
				},
				"Component 98: Arcuate fasciculus postero-inferior - left hemisphere": {
					"subspace": [
						":",
						":",
						":",
						97
					],
					"range": []
				},
				"Component 99: Angular gyrus anterior - right hemisphere": {
					"subspace": [
						":",
						":",
						":",
						98
					],
					"range": []
				},
				"Component 100: Angular sulcus inferior - right hemisphere": {
					"subspace": [
						":",
						":",
						":",
						99
					],
					"range": []
				},
				"Component 101: Temporal pole - left hemisphere": {
					"subspace": [
						":",
						":",
						":",
						100
					],
					"range": []
				},
				"Component 102: Paracentral lobule inferior - left hemisphere": {
					"subspace": [
						":",
						":",
						":",
						101
					],
					"range": []
				},
				"Component 103: Precentral sulcus medial": {
					"subspace": [
						":",
						":",
						":",
						102
					],
					"range": []
				},
				"Component 104: Dorsomedial prefrontal cortex - left hemisphere": {
					"subspace": [
						":",
						":",
						":",
						103
					],
					"range": []
				},
				"Component 105: Amygdala inferior": {
					"subspace": [
						":",
						":",
						":",
						104
					],
					"range": []
				},
				"Component 106: Perirhinal cortex": {
					"subspace": [
						":",
						":",
						":",
						105
					],
					"range": []
				},
				"Component 107: Cuneus middle": {
					"subspace": [
						":",
						":",
						":",
						106
					],
					"range": []
				},
				"Component 108: Callosomarginal sulcus middle": {
					"subspace": [
						":",
						":",
						":",
						107
					],
					"range": []
				},
				"Component 109: Lunate sulcus - right hemisphere": {
					"subspace": [
						":",
						":",
						":",
						108
					],
					"range": []
				},
				"Component 110: Putamen superior": {
					"subspace": [
						":",
						":",
						":",
						109
					],
					"range": []
				},
				"Component 111: Putamen - left hemisphere": {
					"subspace": [
						":",
						":",
						":",
						110
					],
					"range": []
				},
				"Component 112: Frontal pole": {
					"subspace": [
						":",
						":",
						":",
						111
					],
					"range": []
				},
				"Component 113: Forceps minor": {
					"subspace": [
						":",
						":",
						":",
						112
					],
					"range": []
				},
				"Component 114: Superior temporal gyrus medial anterior": {
					"subspace": [
						":",
						":",
						":",
						113
					],
					"range": []
				},
				"Component 115: Middle frontal gyrus anterior - right hemisphere": {
					"subspace": [
						":",
						":",
						":",
						114
					],
					"range": []
				},
				"Component 116: Planum polare superior": {
					"subspace": [
						":",
						":",
						":",
						115
					],
					"range": []
				},
				"Component 117: Dorsomedial prefrontal cortex posterior": {
					"subspace": [
						":",
						":",
						":",
						116
					],
					"range": []
				},
				"Component 118: Superior frontal gyrus postero-superior - left hemisphere": {
					"subspace": [
						":",
						":",
						":",
						117
					],
					"range": []
				},
				"Component 119: Supramarginal gyrus postero-superior - right hemisphere": {
					"subspace": [
						":",
						":",
						":",
						118
					],
					"range": []
				},
				"Component 120: Amygdala": {
					"subspace": [
						":",
						":",
						":",
						119
					],
					"range": []
				},
				"Component 121: Cerebellum VI medial - right hemisphere": {
					"subspace": [
						":",
						":",
						":",
						120
					],
					"range": []
				},
				"Component 122: Lingual gyrus medial": {
					"subspace": [
						":",
						":",
						":",
						121
					],
					"range": []
				},
				"Component 123: Cuneus anterior - right hemisphere": {
					"subspace": [
						":",
						":",
						":",
						122
					],
					"range": []
				},
				"Component 124: Superior frontal sulcus middle - left hemisphere": {
					"subspace": [
						":",
						":",
						":",
						123
					],
					"range": []
				},
				"Component 125: Cerebellum IX inferior": {
					"subspace": [
						":",
						":",
						":",
						124
					],
					"range": []
				},
				"Component 126: Cingulum anterior": {
					"subspace": [
						":",
						":",
						":",
						125
					],
					"range": []
				},
				"Component 127: Inferior temporal sulcus mid-posterior - right hemisphere": {
					"subspace": [
						":",
						":",
						":",
						126
					],
					"range": []
				},
				"Component 128: Cerebellum VI superior - left hemisphere": {
					"subspace": [
						":",
						":",
						":",
						127
					],
					"range": []
				},
				"Component 129: Optic radiation - left hemisphere": {
					"subspace": [
						":",
						":",
						":",
						128
					],
					"range": []
				},
				"Component 130: Corpus callosum genu inferior": {
					"subspace": [
						":",
						":",
						":",
						129
					],
					"range": []
				},
				"Component 131: Precuneus mid-superior - left hemisphere": {
					"subspace": [
						":",
						":",
						":",
						130
					],
					"range": []
				},
				"Component 132: Postcentral gyrus mid-inferior": {
					"subspace": [
						":",
						":",
						":",
						131
					],
					"range": []
				},
				"Component 133: Inferior frontal sulcus posterior - left hemisphere": {
					"subspace": [
						":",
						":",
						":",
						132
					],
					"range": []
				},
				"Component 134: Lateral occipital cortex posterior - left hemisphere": {
					"subspace": [
						":",
						":",
						":",
						133
					],
					"range": []
				},
				"Component 135: Angular gyrus mid-posterior - right hemisphere": {
					"subspace": [
						":",
						":",
						":",
						134
					],
					"range": []
				},
				"Component 136: Temporal pole": {
					"subspace": [
						":",
						":",
						":",
						135
					],
					"range": []
				},
				"Component 137: Cerebellum Crus II posterior - left hemisphere": {
					"subspace": [
						":",
						":",
						":",
						136
					],
					"range": []
				},
				"Component 138: Superior temporal sulcus posterior - left hemisphere": {
					"subspace": [
						":",
						":",
						":",
						137
					],
					"range": []
				},
				"Component 139: Cerebrospinal fluid (between superior precentral gyrus and skull)": {
					"subspace": [
						":",
						":",
						":",
						138
					],
					"range": []
				},
				"Component 140: Lunate sulcus - left hemisphere": {
					"subspace": [
						":",
						":",
						":",
						139
					],
					"range": []
				},
				"Component 141: Cerebellum Crus I medial - right hemisphere": {
					"subspace": [
						":",
						":",
						":",
						140
					],
					"range": []
				},
				"Component 142: Posterior cingulate cortex - left hemisphere": {
					"subspace": [
						":",
						":",
						":",
						141
					],
					"range": []
				},
				"Component 143: Precuneus anterior": {
					"subspace": [
						":",
						":",
						":",
						142
					],
					"range": []
				},
				"Component 144: Intraparietal sulcus middle - left hemisphere": {
					"subspace": [
						":",
						":",
						":",
						143
					],
					"range": []
				},
				"Component 145: Lingual gyrus middle": {
					"subspace": [
						":",
						":",
						":",
						144
					],
					"range": []
				},
				"Component 146: Superior temporal gyrus posterior - right hemisphere": {
					"subspace": [
						":",
						":",
						":",
						145
					],
					"range": []
				},
				"Component 147: Lateral orbital cortex": {
					"subspace": [
						":",
						":",
						":",
						146
					],
					"range": []
				},
				"Component 148: Pons antero-superior": {
					"subspace": [
						":",
						":",
						":",
						147
					],
					"range": []
				},
				"Component 149: Middle frontal sulcus anterior": {
					"subspace": [
						":",
						":",
						":",
						148
					],
					"range": []
				},
				"Component 150: Occipital pole superior - left hemisphere": {
					"subspace": [
						":",
						":",
						":",
						149
					],
					"range": []
				},
				"Component 151: Lingual gyrus mid-posterior - left hemisphere": {
					"subspace": [
						":",
						":",
						":",
						150
					],
					"range": []
				},
				"Component 152: Posterior cingulate cortex superior": {
					"subspace": [
						":",
						":",
						":",
						151
					],
					"range": []
				},
				"Component 153: Inferior frontal sulcus posterior - right hemisphere": {
					"subspace": [
						":",
						":",
						":",
						152
					],
					"range": []
				},
				"Component 154: Cerebrospinal fluid (between angular gyrus and skull LH)": {
					"subspace": [
						":",
						":",
						":",
						153
					],
					"range": []
				},
				"Component 155: Intraparietal sulcus mid-anterior - left hemisphere": {
					"subspace": [
						":",
						":",
						":",
						154
					],
					"range": []
				},
				"Component 156: Arcuate fasciculus postero-inferior - right hemisphere": {
					"subspace": [
						":",
						":",
						":",
						155
					],
					"range": []
				},
				"Component 157: Frontal pole lateral - right hemisphere": {
					"subspace": [
						":",
						":",
						":",
						156
					],
					"range": []
				},
				"Component 158: Cerebellum VIIIb inferior ": {
					"subspace": [
						":",
						":",
						":",
						157
					],
					"range": []
				},
				"Component 159: Parieto-occipital sulcus middle superior - left hemisphere": {
					"subspace": [
						":",
						":",
						":",
						158
					],
					"range": []
				},
				"Component 160: Anterior rami of the lateral fissure - right hemisphere": {
					"subspace": [
						":",
						":",
						":",
						159
					],
					"range": []
				},
				"Component 161: Cingulate gyrus mid-posterior ": {
					"subspace": [
						":",
						":",
						":",
						160
					],
					"range": []
				},
				"Component 162: Superior frontal sulcus posterior - left hemisphere": {
					"subspace": [
						":",
						":",
						":",
						161
					],
					"range": []
				},
				"Component 163: Superior longitudinal fasciculus I posterior - left hemisphere": {
					"subspace": [
						":",
						":",
						":",
						162
					],
					"range": []
				},
				"Component 164: Cerebellum IV inferior": {
					"subspace": [
						":",
						":",
						":",
						163
					],
					"range": []
				},
				"Component 165: Corona radiata superior": {
					"subspace": [
						":",
						":",
						":",
						164
					],
					"range": []
				},
				"Component 166: Insula postero-superior lateral": {
					"subspace": [
						":",
						":",
						":",
						165
					],
					"range": []
				},
				"Component 167: Middle frontal gyrus posterior - left hemisphere": {
					"subspace": [
						":",
						":",
						":",
						166
					],
					"range": []
				},
				"Component 168: Third ventricle": {
					"subspace": [
						":",
						":",
						":",
						167
					],
					"range": []
				},
				"Component 169: Precentral gyrus middle - left hemisphere": {
					"subspace": [
						":",
						":",
						":",
						168
					],
					"range": []
				},
				"Component 170: Callosal sulcus posterior": {
					"subspace": [
						":",
						":",
						":",
						169
					],
					"range": []
				},
				"Component 171: Angular gyrus superior - left hemisphere": {
					"subspace": [
						":",
						":",
						":",
						170
					],
					"range": []
				},
				"Component 172: Superior occipital gyrus - left hemisphere": {
					"subspace": [
						":",
						":",
						":",
						171
					],
					"range": []
				},
				"Component 173: Superior longitudinal fasciculus II posterior - right hemisphere": {
					"subspace": [
						":",
						":",
						":",
						172
					],
					"range": []
				},
				"Component 174: Superior frontal gyrus anterior": {
					"subspace": [
						":",
						":",
						":",
						173
					],
					"range": []
				},
				"Component 175: Cuneus posterior - right hemisphere": {
					"subspace": [
						":",
						":",
						":",
						174
					],
					"range": []
				},
				"Component 176: Superior parts of central and postcentral sulci ": {
					"subspace": [
						":",
						":",
						":",
						175
					],
					"range": []
				},
				"Component 177: Calcarine sulcus mid-anterior": {
					"subspace": [
						":",
						":",
						":",
						176
					],
					"range": []
				},
				"Component 178: Middle temporal gyrus medial - left hemisphere": {
					"subspace": [
						":",
						":",
						":",
						177
					],
					"range": []
				},
				"Component 179: Occipital pole lateral - left hemisphere": {
					"subspace": [
						":",
						":",
						":",
						178
					],
					"range": []
				},
				"Component 180: Fusiform gyrus middle superior - right hemisphere": {
					"subspace": [
						":",
						":",
						":",
						179
					],
					"range": []
				},
				"Component 181: Cerebrospinal fluid (between superior parietal lobule and skull RH)": {
					"subspace": [
						":",
						":",
						":",
						180
					],
					"range": []
				},
				"Component 182: Cerebrospinal fluid (between superior frontal gyrus and skull)": {
					"subspace": [
						":",
						":",
						":",
						181
					],
					"range": []
				},
				"Component 183: Planum temporale": {
					"subspace": [
						":",
						":",
						":",
						182
					],
					"range": []
				},
				"Component 184: Subcentral gyrus - right hemisphere": {
					"subspace": [
						":",
						":",
						":",
						183
					],
					"range": []
				},
				"Component 185: Middle frontal sulcus anterior - left hemisphere": {
					"subspace": [
						":",
						":",
						":",
						184
					],
					"range": []
				},
				"Component 186: Anterior cingulate cortex": {
					"subspace": [
						":",
						":",
						":",
						185
					],
					"range": []
				},
				"Component 187: Inferior occipital gyrus": {
					"subspace": [
						":",
						":",
						":",
						186
					],
					"range": []
				},
				"Component 188: Cerebrospinal fluid (between superior frontal gyrus lateral RH and skull)": {
					"subspace": [
						":",
						":",
						":",
						187
					],
					"range": []
				},
				"Component 189: Arcuate fasciculus postero-superior": {
					"subspace": [
						":",
						":",
						":",
						188
					],
					"range": []
				},
				"Component 190: Superior frontal sulcus anterior - left hemisphere": {
					"subspace": [
						":",
						":",
						":",
						189
					],
					"range": []
				},
				"Component 191: Cingulum middle": {
					"subspace": [
						":",
						":",
						":",
						190
					],
					"range": []
				},
				"Component 192: Frontal pole medial": {
					"subspace": [
						":",
						":",
						":",
						191
					],
					"range": []
				},
				"Component 193: Supramarginal gyrus inferior - left hemisphere": {
					"subspace": [
						":",
						":",
						":",
						192
					],
					"range": []
				},
				"Component 194: Cerebrospinal fluid (between superior cerebellum and limbic lobe)": {
					"subspace": [
						":",
						":",
						":",
						193
					],
					"range": []
				},
				"Component 195: Occipital pole": {
					"subspace": [
						":",
						":",
						":",
						194
					],
					"range": []
				},
				"Component 196: Angular gyrus anterior - left hemisphere": {
					"subspace": [
						":",
						":",
						":",
						195
					],
					"range": []
				},
				"Component 197: Corpus callosum genu": {
					"subspace": [
						":",
						":",
						":",
						196
					],
					"range": []
				},
				"Component 198: Cerebellum VI antero-inferior - left hemisphere": {
					"subspace": [
						":",
						":",
						":",
						197
					],
					"range": []
				},
				"Component 199: Precentral gyrus superior - right hemisphere": {
					"subspace": [
						":",
						":",
						":",
						198
					],
					"range": []
				},
				"Component 200: Occipital pole superior": {
					"subspace": [
						":",
						":",
						":",
						199
					],
					"range": []
				},
				"Component 201: Precentral sulcus mid-superior - left hemisphere": {
					"subspace": [
						":",
						":",
						":",
						200
					],
					"range": []
				},
				"Component 202: Superior occipito-frontal fasciculus middle": {
					"subspace": [
						":",
						":",
						":",
						201
					],
					"range": []
				},
				"Component 203: Middle frontal gyrus mid-posterior - right hemisphere": {
					"subspace": [
						":",
						":",
						":",
						202
					],
					"range": []
				},
				"Component 204: Pons": {
					"subspace": [
						":",
						":",
						":",
						203
					],
					"range": []
				},
				"Component 205: Middle frontal gyrus anterior lateral - right hemisphere": {
					"subspace": [
						":",
						":",
						":",
						204
					],
					"range": []
				},
				"Component 206: Postcentral sulcus superior - right hemisphere": {
					"subspace": [
						":",
						":",
						":",
						205
					],
					"range": []
				},
				"Component 207: Superior temporal sulcus posterior - right hemisphere": {
					"subspace": [
						":",
						":",
						":",
						206
					],
					"range": []
				},
				"Component 208: Corpus callosum genu superior": {
					"subspace": [
						":",
						":",
						":",
						207
					],
					"range": []
				},
				"Component 209: Fourth ventricle": {
					"subspace": [
						":",
						":",
						":",
						208
					],
					"range": []
				},
				"Component 210: Calcarine sulcus middle": {
					"subspace": [
						":",
						":",
						":",
						209
					],
					"range": []
				},
				"Component 211: Postcentral sulcus superior - left hemisphere": {
					"subspace": [
						":",
						":",
						":",
						210
					],
					"range": []
				},
				"Component 212: Precentral gyrus superior - left hemisphere": {
					"subspace": [
						":",
						":",
						":",
						211
					],
					"range": []
				},
				"Component 213: Precentral sulcus mid-superior - right hemisphere": {
					"subspace": [
						":",
						":",
						":",
						212
					],
					"range": []
				},
				"Component 214: Intraparietal sulcus anterior - right hemisphere": {
					"subspace": [
						":",
						":",
						":",
						213
					],
					"range": []
				},
				"Component 215: Superior temporal gyrus medial anterior - right hemisphere": {
					"subspace": [
						":",
						":",
						":",
						214
					],
					"range": []
				},
				"Component 216: Precuneus postero-inferior - right hemisphere": {
					"subspace": [
						":",
						":",
						":",
						215
					],
					"range": []
				},
				"Component 217: Parieto-occipital sulcus postero-superior ": {
					"subspace": [
						":",
						":",
						":",
						216
					],
					"range": []
				},
				"Component 218: Cerebellum III inferior": {
					"subspace": [
						":",
						":",
						":",
						217
					],
					"range": []
				},
				"Component 219: Superior parietal lobule medial - right hemisphere": {
					"subspace": [
						":",
						":",
						":",
						218
					],
					"range": []
				},
				"Component 220: Anterior cingulate cortex superior": {
					"subspace": [
						":",
						":",
						":",
						219
					],
					"range": []
				},
				"Component 221: Middle frontal gyrus postero-inferior - left hemisphere": {
					"subspace": [
						":",
						":",
						":",
						220
					],
					"range": []
				},
				"Component 222: Inferior longitudinal fasciculus": {
					"subspace": [
						":",
						":",
						":",
						221
					],
					"range": []
				},
				"Component 223: Cingulate sulcus middle": {
					"subspace": [
						":",
						":",
						":",
						222
					],
					"range": []
				},
				"Component 224: Subthalamic nuclei": {
					"subspace": [
						":",
						":",
						":",
						223
					],
					"range": []
				},
				"Component 225: Caudate inferior": {
					"subspace": [
						":",
						":",
						":",
						224
					],
					"range": []
				},
				"Component 226: Parietal operculum posterior - right hemisphere": {
					"subspace": [
						":",
						":",
						":",
						225
					],
					"range": []
				},
				"Component 227: Collateral sulcus posterior - right hemisphere": {
					"subspace": [
						":",
						":",
						":",
						226
					],
					"range": []
				},
				"Component 228: Cuneus postero-superior": {
					"subspace": [
						":",
						":",
						":",
						227
					],
					"range": []
				},
				"Component 229: Paracentral sulcus": {
					"subspace": [
						":",
						":",
						":",
						228
					],
					"range": []
				},
				"Component 230: Middle temporal gyrus middle posterior - left hemisphere": {
					"subspace": [
						":",
						":",
						":",
						229
					],
					"range": []
				},
				"Component 231: Inferior temporal sulcus posterior - left hemisphere": {
					"subspace": [
						":",
						":",
						":",
						230
					],
					"range": []
				},
				"Component 232: Occipital pole lateral - right hemisphere": {
					"subspace": [
						":",
						":",
						":",
						231
					],
					"range": []
				},
				"Component 233: Medulla oblongata": {
					"subspace": [
						":",
						":",
						":",
						232
					],
					"range": []
				},
				"Component 234: Cerebellum Crus II posterior": {
					"subspace": [
						":",
						":",
						":",
						233
					],
					"range": []
				},
				"Component 235: Superior temporal sulcus middle-superior - right hemisphere": {
					"subspace": [
						":",
						":",
						":",
						234
					],
					"range": []
				},
				"Component 236: Anterior limb of internal capsule": {
					"subspace": [
						":",
						":",
						":",
						235
					],
					"range": []
				},
				"Component 237: Middle temporal gyrus mid-posterior - right hemisphere": {
					"subspace": [
						":",
						":",
						":",
						236
					],
					"range": []
				},
				"Component 238: Lateral occipital cortex superior - left hemisphere": {
					"subspace": [
						":",
						":",
						":",
						237
					],
					"range": []
				},
				"Component 239: Pars triangularis - right hemisphere": {
					"subspace": [
						":",
						":",
						":",
						238
					],
					"range": []
				},
				"Component 240: Cuneus superior ": {
					"subspace": [
						":",
						":",
						":",
						239
					],
					"range": []
				},
				"Component 241: Superior parietal lobule postero-inferior posterior": {
					"subspace": [
						":",
						":",
						":",
						240
					],
					"range": []
				},
				"Component 242: Superior parietal sulcus - left hemisphere": {
					"subspace": [
						":",
						":",
						":",
						241
					],
					"range": []
				},
				"Component 243: Middle temporal gyrus posterior - left hemisphere": {
					"subspace": [
						":",
						":",
						":",
						242
					],
					"range": []
				},
				"Component 244: Precuneus antero-inferior": {
					"subspace": [
						":",
						":",
						":",
						243
					],
					"range": []
				},
				"Component 245: Cerebrospinal fluid (between middle frontal gyrus posterior and skull RH)": {
					"subspace": [
						":",
						":",
						":",
						244
					],
					"range": []
				},
				"Component 246: Superior occipital sulcus middle - right hemisphere": {
					"subspace": [
						":",
						":",
						":",
						245
					],
					"range": []
				},
				"Component 247: Supramarginal gyrus anterior - right hemisphere": {
					"subspace": [
						":",
						":",
						":",
						246
					],
					"range": []
				},
				"Component 248: Posterior cingulate cortex inferior": {
					"subspace": [
						":",
						":",
						":",
						247
					],
					"range": []
				},
				"Component 249: Lateral fissure anterior - left hemisphere": {
					"subspace": [
						":",
						":",
						":",
						248
					],
					"range": []
				},
				"Component 250: Retrosplenial cortex superior": {
					"subspace": [
						":",
						":",
						":",
						249
					],
					"range": []
				},
				"Component 251: Middle frontal gyrus mid-posterior - left hemisphere": {
					"subspace": [
						":",
						":",
						":",
						250
					],
					"range": []
				},
				"Component 252: Superior temporal gyrus superior - right hemisphere": {
					"subspace": [
						":",
						":",
						":",
						251
					],
					"range": []
				},
				"Component 253: Precuneus middle": {
					"subspace": [
						":",
						":",
						":",
						252
					],
					"range": []
				},
				"Component 254: Subsplenial area": {
					"subspace": [
						":",
						":",
						":",
						253
					],
					"range": []
				},
				"Component 255: Inferior temporal sulcus posterior - right hemisphere": {
					"subspace": [
						":",
						":",
						":",
						254
					],
					"range": []
				},
				"Component 256: Cingulum mid-anterior": {
					"subspace": [
						":",
						":",
						":",
						255
					],
					"range": []
				},
				"Component 257: Cerebellum VI antero-superior - left hemisphere": {
					"subspace": [
						":",
						":",
						":",
						256
					],
					"range": []
				},
				"Component 258: Superior parietal lobule - left hemisphere": {
					"subspace": [
						":",
						":",
						":",
						257
					],
					"range": []
				},
				"Component 259: Cerebellum III superior": {
					"subspace": [
						":",
						":",
						":",
						258
					],
					"range": []
				},
				"Component 260: Cerebellum VI posterior": {
					"subspace": [
						":",
						":",
						":",
						259
					],
					"range": []
				},
				"Component 261: Caudate": {
					"subspace": [
						":",
						":",
						":",
						260
					],
					"range": []
				},
				"Component 262: Parahippocampal gyrus anterior": {
					"subspace": [
						":",
						":",
						":",
						261
					],
					"range": []
				},
				"Component 263: Central operculum posterior - right hemisphere": {
					"subspace": [
						":",
						":",
						":",
						262
					],
					"range": []
				},
				"Component 264: Middle temporal gyrus mid-anterior - left hemisphere": {
					"subspace": [
						":",
						":",
						":",
						263
					],
					"range": []
				},
				"Component 265: Fusiform gyrus posterior - right hemisphere": {
					"subspace": [
						":",
						":",
						":",
						264
					],
					"range": []
				},
				"Component 266: Frontal operculum - right hemisphere": {
					"subspace": [
						":",
						":",
						":",
						265
					],
					"range": []
				},
				"Component 267: Superior frontal gyrus middle - left hemisphere": {
					"subspace": [
						":",
						":",
						":",
						266
					],
					"range": []
				},
				"Component 268: Middle temporal gyrus posterior - right hemisphere": {
					"subspace": [
						":",
						":",
						":",
						267
					],
					"range": []
				},
				"Component 269: Precentral gyrus inferior - left hemisphere": {
					"subspace": [
						":",
						":",
						":",
						268
					],
					"range": []
				},
				"Component 270: Hippocampus": {
					"subspace": [
						":",
						":",
						":",
						269
					],
					"range": []
				},
				"Component 271: Paracingulate gyrus mid-anterior - left hemisphere": {
					"subspace": [
						":",
						":",
						":",
						270
					],
					"range": []
				},
				"Component 272: Cerebellum VIIIb medial": {
					"subspace": [
						":",
						":",
						":",
						271
					],
					"range": []
				},
				"Component 273: Central sulcus mid-superior - right hemisphere": {
					"subspace": [
						":",
						":",
						":",
						272
					],
					"range": []
				},
				"Component 274: Cerebellum VIIIb anterior": {
					"subspace": [
						":",
						":",
						":",
						273
					],
					"range": []
				},
				"Component 275: Cerebrospinal fluid (between superior frontal gyrus superior and skull)": {
					"subspace": [
						":",
						":",
						":",
						274
					],
					"range": []
				},
				"Component 276: Superior parietal lobule postero-superior - left hemisphere": {
					"subspace": [
						":",
						":",
						":",
						275
					],
					"range": []
				},
				"Component 277: Superior frontal sulcus mid-posterior - right hemisphere": {
					"subspace": [
						":",
						":",
						":",
						276
					],
					"range": []
				},
				"Component 278: Middle occipital sulcus - left hemisphere": {
					"subspace": [
						":",
						":",
						":",
						277
					],
					"range": []
				},
				"Component 279: Internal capsule posterior - right hemisphere": {
					"subspace": [
						":",
						":",
						":",
						278
					],
					"range": []
				},
				"Component 280: Occipitotemporal gyrus posterior - left hemisphere": {
					"subspace": [
						":",
						":",
						":",
						279
					],
					"range": []
				},
				"Component 281: Inferior occipital sulcus": {
					"subspace": [
						":",
						":",
						":",
						280
					],
					"range": []
				},
				"Component 282: Middle frontal gyrus anterior - left hemisphere": {
					"subspace": [
						":",
						":",
						":",
						281
					],
					"range": []
				},
				"Component 283: Lateral occipital cortex antero-superior - right hemisphere": {
					"subspace": [
						":",
						":",
						":",
						282
					],
					"range": []
				},
				"Component 284: Cerebellum VI superior lateral": {
					"subspace": [
						":",
						":",
						":",
						283
					],
					"range": []
				},
				"Component 285: Cerebral peduncles": {
					"subspace": [
						":",
						":",
						":",
						284
					],
					"range": []
				},
				"Component 286: Occipital pole inferior": {
					"subspace": [
						":",
						":",
						":",
						285
					],
					"range": []
				},
				"Component 287: Ventromedial prefrontal cortex - left hemisphere": {
					"subspace": [
						":",
						":",
						":",
						286
					],
					"range": []
				},
				"Component 288: Calcarine sulcus anterior": {
					"subspace": [
						":",
						":",
						":",
						287
					],
					"range": []
				},
				"Component 289: Cerebellum Crus I posterior - right hemisphere": {
					"subspace": [
						":",
						":",
						":",
						288
					],
					"range": []
				},
				"Component 290: Precentral sulcus mid-inferior - right hemisphere": {
					"subspace": [
						":",
						":",
						":",
						289
					],
					"range": []
				},
				"Component 291: Dorsomedial prefrontal cortex anterior": {
					"subspace": [
						":",
						":",
						":",
						290
					],
					"range": []
				},
				"Component 292: Inferior temporal sulcus middle - right hemisphere": {
					"subspace": [
						":",
						":",
						":",
						291
					],
					"range": []
				},
				"Component 293: Heschl\u2019s gyrus - left hemisphere": {
					"subspace": [
						":",
						":",
						":",
						292
					],
					"range": []
				},
				"Component 294: Middle frontal gyrus posterior - right hemisphere": {
					"subspace": [
						":",
						":",
						":",
						293
					],
					"range": []
				},
				"Component 295: Parietal operculum - left hemisphere": {
					"subspace": [
						":",
						":",
						":",
						294
					],
					"range": []
				},
				"Component 296: Calcarine cortex mid-posterior - left hemisphere": {
					"subspace": [
						":",
						":",
						":",
						295
					],
					"range": []
				},
				"Component 297: Postcentral sulcus superior": {
					"subspace": [
						":",
						":",
						":",
						296
					],
					"range": []
				},
				"Component 298: Thalamus middle ": {
					"subspace": [
						":",
						":",
						":",
						297
					],
					"range": []
				},
				"Component 299: Superior frontal gyrus medial middle": {
					"subspace": [
						":",
						":",
						":",
						298
					],
					"range": []
				},
				"Component 300: Inferior frontal gyrus posterior - left hemisphere": {
					"subspace": [
						":",
						":",
						":",
						299
					],
					"range": []
				},
				"Component 301: Parieto-occipital sulcus middle inferior - left hemisphere": {
					"subspace": [
						":",
						":",
						":",
						300
					],
					"range": []
				},
				"Component 302: Subparietal sulcus - left hemisphere": {
					"subspace": [
						":",
						":",
						":",
						301
					],
					"range": []
				},
				"Component 303: Internal capsule anterior limb - right hemisphere": {
					"subspace": [
						":",
						":",
						":",
						302
					],
					"range": []
				},
				"Component 304: Precuneus mid-posterior": {
					"subspace": [
						":",
						":",
						":",
						303
					],
					"range": []
				},
				"Component 305: Angular gyrus superior - right hemisphere": {
					"subspace": [
						":",
						":",
						":",
						304
					],
					"range": []
				},
				"Component 306: Central sulcus middle - left hemisphere": {
					"subspace": [
						":",
						":",
						":",
						305
					],
					"range": []
				},
				"Component 307: Superior frontal sulcus middle": {
					"subspace": [
						":",
						":",
						":",
						306
					],
					"range": []
				},
				"Component 308: Globus pallidus": {
					"subspace": [
						":",
						":",
						":",
						307
					],
					"range": []
				},
				"Component 309: Central sulcus inferior - right hemisphere": {
					"subspace": [
						":",
						":",
						":",
						308
					],
					"range": []
				},
				"Component 310: Middle frontal gyrus middle": {
					"subspace": [
						":",
						":",
						":",
						309
					],
					"range": []
				},
				"Component 311: Cerebrospinal fluid (between supramarginal gyrus and skull LH)": {
					"subspace": [
						":",
						":",
						":",
						310
					],
					"range": []
				},
				"Component 312: Superior frontal gyrus middle - right hemisphere": {
					"subspace": [
						":",
						":",
						":",
						311
					],
					"range": []
				},
				"Component 313: Corticospinal tract middle - right hemisphere": {
					"subspace": [
						":",
						":",
						":",
						312
					],
					"range": []
				},
				"Component 314: Cingulate sulcus posterior - right hemisphere": {
					"subspace": [
						":",
						":",
						":",
						313
					],
					"range": []
				},
				"Component 315: Lateral occipital cortex superior - right hemisphere": {
					"subspace": [
						":",
						":",
						":",
						314
					],
					"range": []
				},
				"Component 316: Putamen postero-inferior": {
					"subspace": [
						":",
						":",
						":",
						315
					],
					"range": []
				},
				"Component 317: Cerebellum horizontal fissure medial": {
					"subspace": [
						":",
						":",
						":",
						316
					],
					"range": []
				},
				"Component 318: Superior parietal sulcus - right hemisphere": {
					"subspace": [
						":",
						":",
						":",
						317
					],
					"range": []
				},
				"Component 319: Calcarine cortex anterior ": {
					"subspace": [
						":",
						":",
						":",
						318
					],
					"range": []
				},
				"Component 320: Precentral sulcus superior": {
					"subspace": [
						":",
						":",
						":",
						319
					],
					"range": []
				},
				"Component 321: Cuneus posterior": {
					"subspace": [
						":",
						":",
						":",
						320
					],
					"range": []
				},
				"Component 322: Precentral sulcus inferior - left hemisphere": {
					"subspace": [
						":",
						":",
						":",
						321
					],
					"range": []
				},
				"Component 323: Superior longitudinal fasciculus II posterior - left hemisphere": {
					"subspace": [
						":",
						":",
						":",
						322
					],
					"range": []
				},
				"Component 324: Superior parietal lobule postero-superior - right hemisphere": {
					"subspace": [
						":",
						":",
						":",
						323
					],
					"range": []
				},
				"Component 325: Anterior horizontal ramus of the lateral fissure - left hemisphere": {
					"subspace": [
						":",
						":",
						":",
						324
					],
					"range": []
				},
				"Component 326: Parieto-occipital sulcus mid-anterior - right hemisphere": {
					"subspace": [
						":",
						":",
						":",
						325
					],
					"range": []
				},
				"Component 327: Cingulate sulcus mid-anterior - right hemisphere": {
					"subspace": [
						":",
						":",
						":",
						326
					],
					"range": []
				},
				"Component 328: Caudate - left hemisphere": {
					"subspace": [
						":",
						":",
						":",
						327
					],
					"range": []
				},
				"Component 329: Orbital H-shaped sulcus": {
					"subspace": [
						":",
						":",
						":",
						328
					],
					"range": []
				},
				"Component 330: Central operculum - left hemisphere": {
					"subspace": [
						":",
						":",
						":",
						329
					],
					"range": []
				},
				"Component 331: Parieto-occipital sulcus middle": {
					"subspace": [
						":",
						":",
						":",
						330
					],
					"range": []
				},
				"Component 332: Putamen anterior ": {
					"subspace": [
						":",
						":",
						":",
						331
					],
					"range": []
				},
				"Component 333: Cerebrospinal fluid (between middle frontal gyrus and skull LH)": {
					"subspace": [
						":",
						":",
						":",
						332
					],
					"range": []
				},
				"Component 334: Precentral gyrus mid-superior - left hemisphere": {
					"subspace": [
						":",
						":",
						":",
						333
					],
					"range": []
				},
				"Component 335: Thalamus anterior ": {
					"subspace": [
						":",
						":",
						":",
						334
					],
					"range": []
				},
				"Component 336: Posterior cingulate cortex anterior": {
					"subspace": [
						":",
						":",
						":",
						335
					],
					"range": []
				},
				"Component 337: Superior temporal gyrus posterior - left hemisphere": {
					"subspace": [
						":",
						":",
						":",
						336
					],
					"range": []
				},
				"Component 338: Central sulcus middle": {
					"subspace": [
						":",
						":",
						":",
						337
					],
					"range": []
				},
				"Component 339: Cerebellum IX and cerebellar peduncle ": {
					"subspace": [
						":",
						":",
						":",
						338
					],
					"range": []
				},
				"Component 340: Calcarine sulcus anterior - right hemisphere": {
					"subspace": [
						":",
						":",
						":",
						339
					],
					"range": []
				},
				"Component 341: Cerebellum VI medial": {
					"subspace": [
						":",
						":",
						":",
						340
					],
					"range": []
				},
				"Component 342: Cerebellum V superior": {
					"subspace": [
						":",
						":",
						":",
						341
					],
					"range": []
				},
				"Component 343: Collateral sulcus anterior ": {
					"subspace": [
						":",
						":",
						":",
						342
					],
					"range": []
				},
				"Component 344: Cerebellar peduncles": {
					"subspace": [
						":",
						":",
						":",
						343
					],
					"range": []
				},
				"Component 345: Cerebrospinal fluid (between middle frontal gyrus anterior and skull RH)": {
					"subspace": [
						":",
						":",
						":",
						344
					],
					"range": []
				},
				"Component 346: Cerebellum secondary fissure": {
					"subspace": [
						":",
						":",
						":",
						345
					],
					"range": []
				},
				"Component 347: Superior occipital gyrus inferior - right hemisphere": {
					"subspace": [
						":",
						":",
						":",
						346
					],
					"range": []
				},
				"Component 348: Central sulcus superior ": {
					"subspace": [
						":",
						":",
						":",
						347
					],
					"range": []
				},
				"Component 349: Inferior occipital gyrus anterior - left hemisphere": {
					"subspace": [
						":",
						":",
						":",
						348
					],
					"range": []
				},
				"Component 350: Superior parietal lobule posterior": {
					"subspace": [
						":",
						":",
						":",
						349
					],
					"range": []
				},
				"Component 351: Superior temporal sulcus mid-posterior - left hemisphere": {
					"subspace": [
						":",
						":",
						":",
						350
					],
					"range": []
				},
				"Component 352: Lateral occipital cortex anterior - left hemisphere": {
					"subspace": [
						":",
						":",
						":",
						351
					],
					"range": []
				},
				"Component 353: Planum polare inferior": {
					"subspace": [
						":",
						":",
						":",
						352
					],
					"range": []
				},
				"Component 354: Paracingulate gyrus anterior - left hemisphere": {
					"subspace": [
						":",
						":",
						":",
						353
					],
					"range": []
				},
				"Component 355: Paracingulate sulcus posterior": {
					"subspace": [
						":",
						":",
						":",
						354
					],
					"range": []
				},
				"Component 356: Inferior frontal gyrus anterior - left hemisphere": {
					"subspace": [
						":",
						":",
						":",
						355
					],
					"range": []
				},
				"Component 357: Angular sulcus inferior - left hemisphere": {
					"subspace": [
						":",
						":",
						":",
						356
					],
					"range": []
				},
				"Component 358: Subparietal sulcus - right hemisphere": {
					"subspace": [
						":",
						":",
						":",
						357
					],
					"range": []
				},
				"Component 359: Circular sulcus of the insula anterior": {
					"subspace": [
						":",
						":",
						":",
						358
					],
					"range": []
				},
				"Component 360: Middle temporal gyrus mid-anterior - right hemisphere": {
					"subspace": [
						":",
						":",
						":",
						359
					],
					"range": []
				},
				"Component 361: Cerebrospinal fluid (between intraparietal sulcus and skull LH)": {
					"subspace": [
						":",
						":",
						":",
						360
					],
					"range": []
				},
				"Component 362: Precuneus posterior ": {
					"subspace": [
						":",
						":",
						":",
						361
					],
					"range": []
				},
				"Component 363: Inferior occipital gyrus posterior - left hemisphere": {
					"subspace": [
						":",
						":",
						":",
						362
					],
					"range": []
				},
				"Component 364: Lingual gyrus inferior": {
					"subspace": [
						":",
						":",
						":",
						363
					],
					"range": []
				},
				"Component 365: Angular gyrus postero-inferior - left hemisphere": {
					"subspace": [
						":",
						":",
						":",
						364
					],
					"range": []
				},
				"Component 366: Inferior frontal gyrus anterior - right hemisphere": {
					"subspace": [
						":",
						":",
						":",
						365
					],
					"range": []
				},
				"Component 367: Paracingulate sulcus mid-posterior": {
					"subspace": [
						":",
						":",
						":",
						366
					],
					"range": []
				},
				"Component 368: Frontomarginal gyrus - left hemisphere": {
					"subspace": [
						":",
						":",
						":",
						367
					],
					"range": []
				},
				"Component 369: Middle occipital sulcus - right hemisphere": {
					"subspace": [
						":",
						":",
						":",
						368
					],
					"range": []
				},
				"Component 370: Inferior occipital gyrus - right hemisphere": {
					"subspace": [
						":",
						":",
						":",
						369
					],
					"range": []
				},
				"Component 371: Inferior frontal sulcus anterior - right hemisphere": {
					"subspace": [
						":",
						":",
						":",
						370
					],
					"range": []
				},
				"Component 372: Postcentral sulcus inferior - left hemisphere": {
					"subspace": [
						":",
						":",
						":",
						371
					],
					"range": []
				},
				"Component 373: Middle temporal gyrus postero-inferior - left hemisphere": {
					"subspace": [
						":",
						":",
						":",
						372
					],
					"range": []
				},
				"Component 374: Superior parietal sulcus superior ": {
					"subspace": [
						":",
						":",
						":",
						373
					],
					"range": []
				},
				"Component 375: Cerebellum VI lateral - right hemisphere": {
					"subspace": [
						":",
						":",
						":",
						374
					],
					"range": []
				},
				"Component 376: Cerebellum V - right hemisphere": {
					"subspace": [
						":",
						":",
						":",
						375
					],
					"range": []
				},
				"Component 377: Internal capsule middle - left hemisphere": {
					"subspace": [
						":",
						":",
						":",
						376
					],
					"range": []
				},
				"Component 378: Cingulate sulcus antero-inferior ": {
					"subspace": [
						":",
						":",
						":",
						377
					],
					"range": []
				},
				"Component 379: Middle temporal gyrus middle anterior - left hemisphere": {
					"subspace": [
						":",
						":",
						":",
						378
					],
					"range": []
				},
				"Component 380: Cerebrospinal fluid (between central sulcus and skull LH)": {
					"subspace": [
						":",
						":",
						":",
						379
					],
					"range": []
				},
				"Component 381: Cerebellum VI": {
					"subspace": [
						":",
						":",
						":",
						380
					],
					"range": []
				},
				"Component 382: Cerebrospinal fluid (between central sulcus and skull RH)": {
					"subspace": [
						":",
						":",
						":",
						381
					],
					"range": []
				},
				"Component 383: Corona radiata anterior - left hemisphere": {
					"subspace": [
						":",
						":",
						":",
						382
					],
					"range": []
				},
				"Component 384: Superior occipital sulcus superior - right hemisphere": {
					"subspace": [
						":",
						":",
						":",
						383
					],
					"range": []
				},
				"Component 385: Intermediate primus of Jensen - left hemisphere": {
					"subspace": [
						":",
						":",
						":",
						384
					],
					"range": []
				},
				"Component 386: Lateral occipital cortex antero-superior - left hemisphere": {
					"subspace": [
						":",
						":",
						":",
						385
					],
					"range": []
				},
				"Component 387: Supramarginal gyrus inferior - right hemisphere": {
					"subspace": [
						":",
						":",
						":",
						386
					],
					"range": []
				},
				"Component 388: Insula antero-superior - left hemisphere": {
					"subspace": [
						":",
						":",
						":",
						387
					],
					"range": []
				},
				"Component 389: Callosomarginal sulcus mid-inferior": {
					"subspace": [
						":",
						":",
						":",
						388
					],
					"range": []
				},
				"Component 390: Insula postero-inferior": {
					"subspace": [
						":",
						":",
						":",
						389
					],
					"range": []
				},
				"Component 391: Middle temporal gyrus middle - right hemisphere": {
					"subspace": [
						":",
						":",
						":",
						390
					],
					"range": []
				},
				"Component 392: Retrosplenial cortex inferior": {
					"subspace": [
						":",
						":",
						":",
						391
					],
					"range": []
				},
				"Component 393: Suborbital sulcus": {
					"subspace": [
						":",
						":",
						":",
						392
					],
					"range": []
				},
				"Component 394: Cingulate sulcus anterior - right hemisphere": {
					"subspace": [
						":",
						":",
						":",
						393
					],
					"range": []
				},
				"Component 395: Precuneus postero-superior ": {
					"subspace": [
						":",
						":",
						":",
						394
					],
					"range": []
				},
				"Component 396: Superior longitudinal fasciculus I posterior": {
					"subspace": [
						":",
						":",
						":",
						395
					],
					"range": []
				},
				"Component 397: Middle frontal gyrus anterior lateral - left hemisphere": {
					"subspace": [
						":",
						":",
						":",
						396
					],
					"range": []
				},
				"Component 398: Cerebrospinal fluid (between callosomarginal sulcus and skull RH)": {
					"subspace": [
						":",
						":",
						":",
						397
					],
					"range": []
				},
				"Component 399: Angular sulcus superior - right hemisphere": {
					"subspace": [
						":",
						":",
						":",
						398
					],
					"range": []
				},
				"Component 400: Collateral sulcus middle": {
					"subspace": [
						":",
						":",
						":",
						399
					],
					"range": []
				},
				"Component 401: Pars opercularis - left hemisphere": {
					"subspace": [
						":",
						":",
						":",
						400
					],
					"range": []
				},
				"Component 402: Superior temporal gyrus middle - left hemisphere": {
					"subspace": [
						":",
						":",
						":",
						401
					],
					"range": []
				},
				"Component 403: Occipitotemporal sulcus posterior - left hemisphere": {
					"subspace": [
						":",
						":",
						":",
						402
					],
					"range": []
				},
				"Component 404: Cerebellum Crus I posterior": {
					"subspace": [
						":",
						":",
						":",
						403
					],
					"range": []
				},
				"Component 405: Lateral fissure posterior limb - right hemisphere": {
					"subspace": [
						":",
						":",
						":",
						404
					],
					"range": []
				},
				"Component 406: Caudate nucleus ": {
					"subspace": [
						":",
						":",
						":",
						405
					],
					"range": []
				},
				"Component 407: Lateral ventricles posterior horns": {
					"subspace": [
						":",
						":",
						":",
						406
					],
					"range": []
				},
				"Component 408: Callosal sulcus mid-posterior": {
					"subspace": [
						":",
						":",
						":",
						407
					],
					"range": []
				},
				"Component 409: Supramarginal gyrus antero-inferior - left hemisphere": {
					"subspace": [
						":",
						":",
						":",
						408
					],
					"range": []
				},
				"Component 410: Callosomarginal sulcus superior": {
					"subspace": [
						":",
						":",
						":",
						409
					],
					"range": []
				},
				"Component 411: Angular gyrus antero-inferior - left hemisphere": {
					"subspace": [
						":",
						":",
						":",
						410
					],
					"range": []
				},
				"Component 412: Superior parts of central and postcentral sulci - left hemisphere": {
					"subspace": [
						":",
						":",
						":",
						411
					],
					"range": []
				},
				"Component 413: Precuneus - right hemisphere": {
					"subspace": [
						":",
						":",
						":",
						412
					],
					"range": []
				},
				"Component 414: Superior parts of central and postcentral sulci - right hemisphere": {
					"subspace": [
						":",
						":",
						":",
						413
					],
					"range": []
				},
				"Component 415: Thalamus - left hemisphere": {
					"subspace": [
						":",
						":",
						":",
						414
					],
					"range": []
				},
				"Component 416: Angular gyrus postero-superior - left hemisphere": {
					"subspace": [
						":",
						":",
						":",
						415
					],
					"range": []
				},
				"Component 417: Paracentral lobule superior": {
					"subspace": [
						":",
						":",
						":",
						416
					],
					"range": []
				},
				"Component 418: Angular gyrus posterior - right hemisphere": {
					"subspace": [
						":",
						":",
						":",
						417
					],
					"range": []
				},
				"Component 419: Calcarine sulcus posterior medial": {
					"subspace": [
						":",
						":",
						":",
						418
					],
					"range": []
				},
				"Component 420: Paracingulate sulcus posterior - left hemisphere": {
					"subspace": [
						":",
						":",
						":",
						419
					],
					"range": []
				},
				"Component 421: Thalamus medial": {
					"subspace": [
						":",
						":",
						":",
						420
					],
					"range": []
				},
				"Component 422: Fusiform gyrus middle inferior - right hemisphere": {
					"subspace": [
						":",
						":",
						":",
						421
					],
					"range": []
				},
				"Component 423: Caudate nucleus tail": {
					"subspace": [
						":",
						":",
						":",
						422
					],
					"range": []
				},
				"Component 424: Parieto-occipital sulcus postero-inferior - right hemisphere": {
					"subspace": [
						":",
						":",
						":",
						423
					],
					"range": []
				},
				"Component 425: Cerebellum Crus I superior": {
					"subspace": [
						":",
						":",
						":",
						424
					],
					"range": []
				},
				"Component 426: Temporal pole - right hemisphere": {
					"subspace": [
						":",
						":",
						":",
						425
					],
					"range": []
				},
				"Component 427: Lingual gyrus anterior": {
					"subspace": [
						":",
						":",
						":",
						426
					],
					"range": []
				},
				"Component 428: Cerebrospinal fluid (between postcentral gyrus and skull)": {
					"subspace": [
						":",
						":",
						":",
						427
					],
					"range": []
				},
				"Component 429: Cerebellum Crus II - right hemisphere": {
					"subspace": [
						":",
						":",
						":",
						428
					],
					"range": []
				},
				"Component 430: Corpus callosum anterior body": {
					"subspace": [
						":",
						":",
						":",
						429
					],
					"range": []
				},
				"Component 431: Superior occipital gyrus - right hemisphere": {
					"subspace": [
						":",
						":",
						":",
						430
					],
					"range": []
				},
				"Component 432: Subparietal sulcus inferior - left hemisphere": {
					"subspace": [
						":",
						":",
						":",
						431
					],
					"range": []
				},
				"Component 433: Intraparietal sulcus mid-posterior - right hemisphere": {
					"subspace": [
						":",
						":",
						":",
						432
					],
					"range": []
				},
				"Component 434: Hippocampus posterior": {
					"subspace": [
						":",
						":",
						":",
						433
					],
					"range": []
				},
				"Component 435: Cuneus anterior": {
					"subspace": [
						":",
						":",
						":",
						434
					],
					"range": []
				},
				"Component 436: Precuneus antero-superior": {
					"subspace": [
						":",
						":",
						":",
						435
					],
					"range": []
				},
				"Component 437: Central sulcus inferior": {
					"subspace": [
						":",
						":",
						":",
						436
					],
					"range": []
				},
				"Component 438: Central sulcus mid-inferior - right hemisphere": {
					"subspace": [
						":",
						":",
						":",
						437
					],
					"range": []
				},
				"Component 439: Precentral sulcus inferior - right hemisphere": {
					"subspace": [
						":",
						":",
						":",
						438
					],
					"range": []
				},
				"Component 440: Superior longitudinal fasciculus I": {
					"subspace": [
						":",
						":",
						":",
						439
					],
					"range": []
				},
				"Component 441: Middle frontal gyrus anterior medial - right hemisphere": {
					"subspace": [
						":",
						":",
						":",
						440
					],
					"range": []
				},
				"Component 442: Cerebellum Crus I posterior - left hemisphere": {
					"subspace": [
						":",
						":",
						":",
						441
					],
					"range": []
				},
				"Component 443: Superior temporal sulcus middle - left hemisphere": {
					"subspace": [
						":",
						":",
						":",
						442
					],
					"range": []
				},
				"Component 444: Cerebrospinal fluid (between intraparietal sulcus and skull RH)": {
					"subspace": [
						":",
						":",
						":",
						443
					],
					"range": []
				},
				"Component 445: Forceps minor - right hemisphere": {
					"subspace": [
						":",
						":",
						":",
						444
					],
					"range": []
				},
				"Component 446: Forceps major": {
					"subspace": [
						":",
						":",
						":",
						445
					],
					"range": []
				},
				"Component 447: Superior temporal sulcus middle-inferior - right hemisphere": {
					"subspace": [
						":",
						":",
						":",
						446
					],
					"range": []
				},
				"Component 448: Lingual gyrus mid-anterior - left hemisphere": {
					"subspace": [
						":",
						":",
						":",
						447
					],
					"range": []
				},
				"Component 449: Middle frontal gyrus mid-posterior lateral - left hemisphere": {
					"subspace": [
						":",
						":",
						":",
						448
					],
					"range": []
				},
				"Component 450: Cerebellum superior posterior fissure - left hemisphere": {
					"subspace": [
						":",
						":",
						":",
						449
					],
					"range": []
				},
				"Component 451: Fusiform gyrus middle - right hemisphere": {
					"subspace": [
						":",
						":",
						":",
						450
					],
					"range": []
				},
				"Component 452: Medulla oblongata superior": {
					"subspace": [
						":",
						":",
						":",
						451
					],
					"range": []
				},
				"Component 453: Superior occipital gyrus superior - right hemisphere": {
					"subspace": [
						":",
						":",
						":",
						452
					],
					"range": []
				},
				"Component 454: Superior longitudinal fasciculus III posterior - right hemisphere": {
					"subspace": [
						":",
						":",
						":",
						453
					],
					"range": []
				},
				"Component 455: Frontomarginal sulcus": {
					"subspace": [
						":",
						":",
						":",
						454
					],
					"range": []
				},
				"Component 456: Superior longitudinal fasciculus III middle - right hemisphere": {
					"subspace": [
						":",
						":",
						":",
						455
					],
					"range": []
				},
				"Component 457: Inferior frontal sulcus mid-anterior - left hemisphere": {
					"subspace": [
						":",
						":",
						":",
						456
					],
					"range": []
				},
				"Component 458: Cerebrospinal fluid (between superior frontal gyrus middle superior and skull)": {
					"subspace": [
						":",
						":",
						":",
						457
					],
					"range": []
				},
				"Component 459: Central sulcus - left hemisphere": {
					"subspace": [
						":",
						":",
						":",
						458
					],
					"range": []
				},
				"Component 460: Intraparietal sulcus posterior - right hemisphere": {
					"subspace": [
						":",
						":",
						":",
						459
					],
					"range": []
				},
				"Component 461: Precuneus inferior ": {
					"subspace": [
						":",
						":",
						":",
						460
					],
					"range": []
				},
				"Component 462: Heschl\u2019s gyrus - right hemisphere": {
					"subspace": [
						":",
						":",
						":",
						461
					],
					"range": []
				},
				"Component 463: Intraparietal sulcus posterior - left hemisphere": {
					"subspace": [
						":",
						":",
						":",
						462
					],
					"range": []
				},
				"Component 464: Lateral ventricles anterior horns": {
					"subspace": [
						":",
						":",
						":",
						463
					],
					"range": []
				},
				"Component 465: Cerebrospinal fluid (between postcentral sulcus and skull RH)": {
					"subspace": [
						":",
						":",
						":",
						464
					],
					"range": []
				},
				"Component 466: Central sulcus superior - left hemisphere": {
					"subspace": [
						":",
						":",
						":",
						465
					],
					"range": []
				},
				"Component 467: External capsule middle - left hemisphere": {
					"subspace": [
						":",
						":",
						":",
						466
					],
					"range": []
				},
				"Component 468: Putamen - right hemisphere": {
					"subspace": [
						":",
						":",
						":",
						467
					],
					"range": []
				},
				"Component 469: Cerebrospinal fluid (between superior parietal lobule posterior and skull RH)": {
					"subspace": [
						":",
						":",
						":",
						468
					],
					"range": []
				},
				"Component 470: Insula superior": {
					"subspace": [
						":",
						":",
						":",
						469
					],
					"range": []
				},
				"Component 471: Heschl\u2019s gyrus posterior - right hemisphere": {
					"subspace": [
						":",
						":",
						":",
						470
					],
					"range": []
				},
				"Component 472: Optic radiation - right hemisphere": {
					"subspace": [
						":",
						":",
						":",
						471
					],
					"range": []
				},
				"Component 473: Anterior parts of occipitotemporal and collateral sulci - left hemisphere": {
					"subspace": [
						":",
						":",
						":",
						472
					],
					"range": []
				},
				"Component 474: Cingulate sulcus mid-posterior ": {
					"subspace": [
						":",
						":",
						":",
						473
					],
					"range": []
				},
				"Component 475: Middle frontal sulcus mid-anterior - left hemisphere": {
					"subspace": [
						":",
						":",
						":",
						474
					],
					"range": []
				},
				"Component 476: Ventromedial prefrontal cortex posterior": {
					"subspace": [
						":",
						":",
						":",
						475
					],
					"range": []
				},
				"Component 477: Cerebrospinal fluid (between superior parietal lobule and skull LH)": {
					"subspace": [
						":",
						":",
						":",
						476
					],
					"range": []
				},
				"Component 478: Cerebellum VI posterior - left hemisphere": {
					"subspace": [
						":",
						":",
						":",
						477
					],
					"range": []
				},
				"Component 479: Ventromedial prefrontal cortex anterior": {
					"subspace": [
						":",
						":",
						":",
						478
					],
					"range": []
				},
				"Component 480: Putamen postero-superior": {
					"subspace": [
						":",
						":",
						":",
						479
					],
					"range": []
				},
				"Component 481: Cerebellum VI  - left hemisphere": {
					"subspace": [
						":",
						":",
						":",
						480
					],
					"range": []
				},
				"Component 482: Cerebellum Crus I superior - right hemisphere": {
					"subspace": [
						":",
						":",
						":",
						481
					],
					"range": []
				},
				"Component 483: Superior longitudinal fasciculus III anterior - right hemisphere": {
					"subspace": [
						":",
						":",
						":",
						482
					],
					"range": []
				},
				"Component 484: Midbrain inferior": {
					"subspace": [
						":",
						":",
						":",
						483
					],
					"range": []
				},
				"Component 485: Postcentral gyrus middle - right hemisphere": {
					"subspace": [
						":",
						":",
						":",
						484
					],
					"range": []
				},
				"Component 486: Paracingulate sulcus mid-posterior - right hemisphere": {
					"subspace": [
						":",
						":",
						":",
						485
					],
					"range": []
				},
				"Component 487: Fusiform gyrus posterior - left hemisphere": {
					"subspace": [
						":",
						":",
						":",
						486
					],
					"range": []
				},
				"Component 488: Hippocampus middle": {
					"subspace": [
						":",
						":",
						":",
						487
					],
					"range": []
				},
				"Component 489: Corpus callosum rostrum": {
					"subspace": [
						":",
						":",
						":",
						488
					],
					"range": []
				},
				"Component 490: Orbitofrontal cortex": {
					"subspace": [
						":",
						":",
						":",
						489
					],
					"range": []
				},
				"Component 491: Cerebellum Crus II medial - right hemisphere": {
					"subspace": [
						":",
						":",
						":",
						490
					],
					"range": []
				},
				"Component 492: Cerebellum IV superior": {
					"subspace": [
						":",
						":",
						":",
						491
					],
					"range": []
				},
				"Component 493: Cingulate sulcus posterior - left hemisphere": {
					"subspace": [
						":",
						":",
						":",
						492
					],
					"range": []
				},
				"Component 494: Superior parietal lobule superior": {
					"subspace": [
						":",
						":",
						":",
						493
					],
					"range": []
				},
				"Component 495: Lingual gyrus middle - right hemisphere": {
					"subspace": [
						":",
						":",
						":",
						494
					],
					"range": []
				},
				"Component 496: Corpus callosum isthmus posterior": {
					"subspace": [
						":",
						":",
						":",
						495
					],
					"range": []
				},
				"Component 497: Precuneus superior": {
					"subspace": [
						":",
						":",
						":",
						496
					],
					"range": []
				},
				"Component 498: Inferior occipital gyrus posterior - right hemisphere": {
					"subspace": [
						":",
						":",
						":",
						497
					],
					"range": []
				},
				"Component 499: Callosomarginal sulcus inferior": {
					"subspace": [
						":",
						":",
						":",
						498
					],
					"range": []
				},
				"Component 500: Superior frontal sulcus posterior - right hemisphere": {
					"subspace": [
						":",
						":",
						":",
						499
					],
					"range": []
				},
				"Component 501: Inferior fronto-occipital fasciculus posterior - left hemisphere": {
					"subspace": [
						":",
						":",
						":",
						500
					],
					"range": []
				},
				"Component 502: Central sulcus mid-superior ": {
					"subspace": [
						":",
						":",
						":",
						501
					],
					"range": []
				},
				"Component 503: Cerebrospinal fluid (between inferior frontal sulcus and skull LH)": {
					"subspace": [
						":",
						":",
						":",
						502
					],
					"range": []
				},
				"Component 504: Cerebellum Crus I anterior - left hemisphere": {
					"subspace": [
						":",
						":",
						":",
						503
					],
					"range": []
				},
				"Component 505: Central operculum anterior - right hemisphere": {
					"subspace": [
						":",
						":",
						":",
						504
					],
					"range": []
				},
				"Component 506: Corpus callosum splenium": {
					"subspace": [
						":",
						":",
						":",
						505
					],
					"range": []
				},
				"Component 507: Superior occipital sulcus - right hemisphere": {
					"subspace": [
						":",
						":",
						":",
						506
					],
					"range": []
				},
				"Component 508: Superior temporal gyrus superior - left hemisphere": {
					"subspace": [
						":",
						":",
						":",
						507
					],
					"range": []
				},
				"Component 509: Middle temporal gyrus mid-posterior - left hemisphere": {
					"subspace": [
						":",
						":",
						":",
						508
					],
					"range": []
				},
				"Component 510: Insula postero-inferior - right hemisphere": {
					"subspace": [
						":",
						":",
						":",
						509
					],
					"range": []
				},
				"Component 511: Parieto-occipital sulcus middle - left hemisphere": {
					"subspace": [
						":",
						":",
						":",
						510
					],
					"range": []
				},
				"Component 512: Precentral sulcus superior - right hemisphere": {
					"subspace": [
						":",
						":",
						":",
						511
					],
					"range": []
				}
			},
			"colormap": "magma"
		}
	]
}
