{
	"space": {
		"@id": "minds/core/referencespace/v1.0.0/d5717c4a-0fa1-46e6-918c-b8003069ade8"
	},
	"parcellation": {
		"@id": "minds/core/parcellationatlas/v1.0.0/ebb923ba-b4d5-4b82-8088-fa9215c2e1fe-v4"
	},
	"map_type": "labelled",
	"regions": {
		"lateral olfactory tract": [
			{
				"map": 0,
				"index": 180
			}
		],
		"corpus callosum and associated subcortical white matter": [
			{
				"map": 0,
				"index": 67
			}
		],
		"anterior commissure, anterior limb": [
			{
				"map": 0,
				"index": 36
			}
		],
		"anterior commissure, posterior limb": [
			{
				"map": 0,
				"index": 37
			}
		],
		"anterior commissure, intrabulbar part": [
			{
				"map": 0,
				"index": 73
			}
		],
		"alveus of the hippocampus": [
			{
				"map": 0,
				"index": 6
			}
		],
		"ventral hippocampal commissure": [
			{
				"map": 0,
				"index": 38
			}
		],
		"fornix": [
			{
				"map": 0,
				"index": 52
			}
		],
		"fimbria of the hippocampus": [
			{
				"map": 0,
				"index": 59
			}
		],
		"corticofugal tract and corona radiata": [
			{
				"map": 0,
				"index": 1
			}
		],
		"pyramidal decussation": [
			{
				"map": 0,
				"index": 85
			}
		],
		"medial lemniscus, unspecified": [
			{
				"map": 0,
				"index": 34
			}
		],
		"medial lemniscus decussation": [
			{
				"map": 0,
				"index": 84
			}
		],
		"external medullary lamina, unspecified": [
			{
				"map": 0,
				"index": 249
			}
		],
		"external medullary lamina, auditory radiation": [
			{
				"map": 0,
				"index": 157
			}
		],
		"internal medullary lamina": [
			{
				"map": 0,
				"index": 291
			}
		],
		"intramedullary thalamic area": [
			{
				"map": 0,
				"index": 290
			}
		],
		"superior cerebellar peduncle and prerubral field": [
			{
				"map": 0,
				"index": 270
			}
		],
		"pretectothalamic lamina": [
			{
				"map": 0,
				"index": 239
			}
		],
		"mammillotegmental tract": [
			{
				"map": 0,
				"index": 53
			}
		],
		"commissural stria terminalis": [
			{
				"map": 0,
				"index": 54
			}
		],
		"fasciculus retroflexus": [
			{
				"map": 0,
				"index": 60
			}
		],
		"stria medullaris thalami": [
			{
				"map": 0,
				"index": 61
			}
		],
		"stria terminalis": [
			{
				"map": 0,
				"index": 62
			}
		],
		"habenular commissure": [
			{
				"map": 0,
				"index": 80
			}
		],
		"posterior commissure": [
			{
				"map": 0,
				"index": 63
			}
		],
		"facial nerve, unspecified": [
			{
				"map": 0,
				"index": 35
			}
		],
		"ascending fibers of the facial nerve": [
			{
				"map": 0,
				"index": 72
			}
		],
		"genu of the facial nerve": [
			{
				"map": 0,
				"index": 57
			}
		],
		"optic nerve": [
			{
				"map": 0,
				"index": 41
			}
		],
		"optic tract and optic chiasm": [
			{
				"map": 0,
				"index": 42
			}
		],
		"supraoptic decussation": [
			{
				"map": 0,
				"index": 83
			}
		],
		"commissure of the superior colliculus": [
			{
				"map": 0,
				"index": 46
			}
		],
		"brachium of the superior colliculus": [
			{
				"map": 0,
				"index": 68
			}
		],
		"inferior colliculus, commissure": [
			{
				"map": 0,
				"index": 69
			}
		],
		"inferior colliculus, brachium": [
			{
				"map": 0,
				"index": 146
			}
		],
		"inferior cerebellar peduncle": [
			{
				"map": 0,
				"index": 7
			}
		],
		"middle cerebellar peduncle": [
			{
				"map": 0,
				"index": 78
			}
		],
		"transverse fibers of the pons": [
			{
				"map": 0,
				"index": 79
			}
		],
		"lateral lemniscus, commissure": [
			{
				"map": 0,
				"index": 140
			}
		],
		"lateral lemniscus, unspecified": [
			{
				"map": 0,
				"index": 141
			}
		],
		"acoustic striae": [
			{
				"map": 0,
				"index": 129
			}
		],
		"trapezoid body": [
			{
				"map": 0,
				"index": 130
			}
		],
		"spinal trigeminal tract": [
			{
				"map": 0,
				"index": 76
			}
		],
		"Glomerular layer of the accessory olfactory bulb": [
			{
				"map": 0,
				"index": 64
			}
		],
		"Glomerular layer of the olfactory bulb": [
			{
				"map": 0,
				"index": 65
			}
		],
		"Olfactory bulb, unspecified": [
			{
				"map": 0,
				"index": 66
			}
		],
		"Nucleus of the lateral olfactory tract": [
			{
				"map": 0,
				"index": 502
			}
		],
		"Fasciola cinereum": [
			{
				"map": 0,
				"index": 99
			}
		],
		"Subiculum": [
			{
				"map": 0,
				"index": 100
			}
		],
		"Cornu ammonis 1": [
			{
				"map": 0,
				"index": 98
			}
		],
		"Cornu ammonis 2": [
			{
				"map": 0,
				"index": 97
			}
		],
		"Cornu ammonis 3": [
			{
				"map": 0,
				"index": 95
			}
		],
		"Dentate gyrus": [
			{
				"map": 0,
				"index": 96
			}
		],
		"Postrhinal cortex": [
			{
				"map": 0,
				"index": 108
			}
		],
		"Presubiculum": [
			{
				"map": 0,
				"index": 109
			}
		],
		"Parasubiculum": [
			{
				"map": 0,
				"index": 110
			}
		],
		"Perirhinal area 35": [
			{
				"map": 0,
				"index": 112
			}
		],
		"Perirhinal area 36": [
			{
				"map": 0,
				"index": 113
			}
		],
		"Medial entorhinal cortex": [
			{
				"map": 0,
				"index": 114
			}
		],
		"Lateral entorhinal cortex": [
			{
				"map": 0,
				"index": 115
			}
		],
		"Piriform cortex, layer 1": [
			{
				"map": 0,
				"index": 181
			}
		],
		"Piriform cortex, layer 2": [
			{
				"map": 0,
				"index": 182
			}
		],
		"Piriform cortex, layer 3": [
			{
				"map": 0,
				"index": 183
			}
		],
		"Cingulate area 1": [
			{
				"map": 0,
				"index": 411
			}
		],
		"Cingulate area 2": [
			{
				"map": 0,
				"index": 10
			}
		],
		"Retrosplenial dysgranular area": [
			{
				"map": 0,
				"index": 427
			}
		],
		"Retrosplenial granular area": [
			{
				"map": 0,
				"index": 430
			}
		],
		"Agranular insular cortex, ventral area": [
			{
				"map": 0,
				"index": 409
			}
		],
		"Agranular insular cortex dorsal area ": [
			{
				"map": 0,
				"index": 410
			}
		],
		"Agranular insular cortex, posterior area ": [
			{
				"map": 0,
				"index": 424
			}
		],
		"Dysgranular insular cortex": [
			{
				"map": 0,
				"index": 414
			}
		],
		"Granular insular cortex": [
			{
				"map": 0,
				"index": 416
			}
		],
		"Frontal association cortex": [
			{
				"map": 0,
				"index": 77
			}
		],
		"Medial orbital area": [
			{
				"map": 0,
				"index": 403
			}
		],
		"Ventral orbital area": [
			{
				"map": 0,
				"index": 402
			}
		],
		"Ventrolateral orbital area": [
			{
				"map": 0,
				"index": 400
			}
		],
		"Lateral orbital area": [
			{
				"map": 0,
				"index": 401
			}
		],
		"Dorsolateral orbital area": [
			{
				"map": 0,
				"index": 404
			}
		],
		"Prelimbic area": [
			{
				"map": 0,
				"index": 405
			}
		],
		"Infralimbic area": [
			{
				"map": 0,
				"index": 413
			}
		],
		"Primary motor area": [
			{
				"map": 0,
				"index": 408
			}
		],
		"Secondary motor area": [
			{
				"map": 0,
				"index": 406
			}
		],
		"Frontal association area 3": [
			{
				"map": 0,
				"index": 407
			}
		],
		"Primary somatosensory area, face representation": [
			{
				"map": 0,
				"index": 420
			}
		],
		"Primary somatosensory area, barrel field": [
			{
				"map": 0,
				"index": 425
			}
		],
		"Primary somatosensory area, dysgranular zone": [
			{
				"map": 0,
				"index": 418
			}
		],
		"Primary somatosensory area, forelimb representation": [
			{
				"map": 0,
				"index": 417
			}
		],
		"Primary somatosensory area, hindlimb representation": [
			{
				"map": 0,
				"index": 423
			}
		],
		"Primary somatosensory area, trunk representation": [
			{
				"map": 0,
				"index": 429
			}
		],
		"Secondary somatosensory area": [
			{
				"map": 0,
				"index": 422
			}
		],
		"Parietal association cortex, medial area": [
			{
				"map": 0,
				"index": 433
			}
		],
		"Parietal association cortex, lateral area": [
			{
				"map": 0,
				"index": 432
			}
		],
		"Parietal association cortex, posterior area ": [
			{
				"map": 0,
				"index": 436
			}
		],
		"Primary visual area": [
			{
				"map": 0,
				"index": 442
			}
		],
		"Secondary visual area, medial part": [
			{
				"map": 0,
				"index": 448
			}
		],
		"Secondary visual area, lateral part": [
			{
				"map": 0,
				"index": 443
			}
		],
		"Temporal association cortex": [
			{
				"map": 0,
				"index": 444
			}
		],
		"Primary auditory area": [
			{
				"map": 0,
				"index": 151
			}
		],
		"Secondary auditory area, dorsal part": [
			{
				"map": 0,
				"index": 152
			}
		],
		"Secondary auditory area, ventral part": [
			{
				"map": 0,
				"index": 153
			}
		],
		"Claustrum": [
			{
				"map": 0,
				"index": 412
			}
		],
		"Endopiriform nucleus": [
			{
				"map": 0,
				"index": 500
			}
		],
		"Amygdaloid area, unspecified": [
			{
				"map": 0,
				"index": 501
			}
		],
		"Caudate putamen": [
			{
				"map": 0,
				"index": 197
			}
		],
		"Nucleus accumbens, core": [
			{
				"map": 0,
				"index": 184
			}
		],
		"Nucleus accumbens, shell": [
			{
				"map": 0,
				"index": 192
			}
		],
		"Ventral striatal region, unspecified": [
			{
				"map": 0,
				"index": 199
			}
		],
		"Globus pallidus external, medial part": [
			{
				"map": 0,
				"index": 195
			}
		],
		"Globus pallidus external, lateral part": [
			{
				"map": 0,
				"index": 198
			}
		],
		"Entopeduncular nucleus": [
			{
				"map": 0,
				"index": 32
			}
		],
		"Ventral pallidum": [
			{
				"map": 0,
				"index": 193
			}
		],
		"Basal forebrain region, unspecified": [
			{
				"map": 0,
				"index": 82
			}
		],
		"Bed nucleus of the stria terminalis": [
			{
				"map": 0,
				"index": 93
			}
		],
		"Septal region": [
			{
				"map": 0,
				"index": 40
			}
		],
		"Subthalamic nucleus": [
			{
				"map": 0,
				"index": 3
			}
		],
		"Reticular (pre)thalamic nucleus, unspecified": [
			{
				"map": 0,
				"index": 200
			}
		],
		"Reticular (pre)thalamic nucleus, auditory segment": [
			{
				"map": 0,
				"index": 164
			}
		],
		"Zona incerta, dorsal part": [
			{
				"map": 0,
				"index": 235
			}
		],
		"Zona incerta, ventral part": [
			{
				"map": 0,
				"index": 236
			}
		],
		"Zona incerta, rostral part": [
			{
				"map": 0,
				"index": 257
			}
		],
		"Zona incerta, caudal part": [
			{
				"map": 0,
				"index": 287
			}
		],
		"Zona incerta, A13 dopamine cells": [
			{
				"map": 0,
				"index": 238
			}
		],
		"Zona incerta, A11 dopamine cells": [
			{
				"map": 0,
				"index": 284
			}
		],
		"Fields of Forel": [
			{
				"map": 0,
				"index": 280
			}
		],
		"Pregeniculate nucleus": [
			{
				"map": 0,
				"index": 204
			}
		],
		"Subgeniculate nucleus": [
			{
				"map": 0,
				"index": 281
			}
		],
		"Intergeniculate leaflet": [
			{
				"map": 0,
				"index": 272
			}
		],
		"Lateral habenular nucleus": [
			{
				"map": 0,
				"index": 206
			}
		],
		"Medial habenular nucleus": [
			{
				"map": 0,
				"index": 207
			}
		],
		"Nucleus of the stria medullaris": [
			{
				"map": 0,
				"index": 81
			}
		],
		"Pineal gland": [
			{
				"map": 0,
				"index": 43
			}
		],
		"Anterodorsal thalamic nucleus": [
			{
				"map": 0,
				"index": 213
			}
		],
		"Anteroventral thalamic nucleus, dorsomedial part": [
			{
				"map": 0,
				"index": 214
			}
		],
		"Anteroventral thalamic nucleus, ventrolateral part": [
			{
				"map": 0,
				"index": 215
			}
		],
		"Anteromedial thalamic nucleus": [
			{
				"map": 0,
				"index": 254
			}
		],
		"Interanteromedial thalamic nucleus": [
			{
				"map": 0,
				"index": 255
			}
		],
		"Dorsal-caudal midline group of the dorsal thalamus": [
			{
				"map": 0,
				"index": 1087
			}
		],
		"Paraventricular thalamic nuclei (anterior and posterior)": [
			{
				"map": 0,
				"index": 242
			}
		],
		"Intermediodorsal thalamic nucleus": [
			{
				"map": 0,
				"index": 260
			}
		],
		"Parataenial thalamic nucleus": [
			{
				"map": 0,
				"index": 211
			}
		],
		"Subparafascicular nucleus": [
			{
				"map": 0,
				"index": 278
			}
		],
		"Posterior intralaminar nucleus": [
			{
				"map": 0,
				"index": 208
			}
		],
		"Rhomboid thalamic nucleus": [
			{
				"map": 0,
				"index": 216
			}
		],
		"Reuniens thalamic nucleus": [
			{
				"map": 0,
				"index": 219
			}
		],
		"Retroreuniens thalamic nucleus": [
			{
				"map": 0,
				"index": 268
			}
		],
		"Xiphoid thalamic nucleus": [
			{
				"map": 0,
				"index": 218
			}
		],
		"Mediodorsal thalamic nucleus, lateral part": [
			{
				"map": 0,
				"index": 232
			}
		],
		"Mediodorsal thalamic nucleus, central part": [
			{
				"map": 0,
				"index": 233
			}
		],
		"Mediodorsal thalamic nucleus, medial part": [
			{
				"map": 0,
				"index": 240
			}
		],
		"Ventral anterior thalamic nucleus": [
			{
				"map": 0,
				"index": 293
			}
		],
		"Ventromedial thalamic nucleus": [
			{
				"map": 0,
				"index": 221
			}
		],
		"Ventrolateral thalamic nucleus": [
			{
				"map": 0,
				"index": 231
			}
		],
		"Angular thalamic nucleus": [
			{
				"map": 0,
				"index": 223
			}
		],
		"Ventral posteromedial thalamic nucleus": [
			{
				"map": 0,
				"index": 227
			}
		],
		"Ventral posterolateral thalamic nucleus": [
			{
				"map": 0,
				"index": 294
			}
		],
		"Ventral posterior nucleus of the thalamus, parvicellular part": [
			{
				"map": 0,
				"index": 266
			}
		],
		"Submedius thalamic nucleus": [
			{
				"map": 0,
				"index": 222
			}
		],
		"Paracentral thalamic nucleus": [
			{
				"map": 0,
				"index": 246
			}
		],
		"Central medial thalamic nucleus": [
			{
				"map": 0,
				"index": 247
			}
		],
		"Central lateral thalamic nucleus": [
			{
				"map": 0,
				"index": 248
			}
		],
		"Parafascicular thalamic nucleus": [
			{
				"map": 0,
				"index": 267
			}
		],
		"Ethmoid-Limitans nucleus": [
			{
				"map": 0,
				"index": 282
			}
		],
		"Posterior thalamic nucleus": [
			{
				"map": 0,
				"index": 230
			}
		],
		"Posterior thalamic nuclear group, triangular part": [
			{
				"map": 0,
				"index": 210
			}
		],
		"Lateral posterior thalamic nucleus, mediorostral part": [
			{
				"map": 0,
				"index": 285
			}
		],
		"Lateral posterior thalamic nucleus, mediocaudal part": [
			{
				"map": 0,
				"index": 286
			}
		],
		"Lateral posterior thalamic nucleus, lateral part": [
			{
				"map": 0,
				"index": 283
			}
		],
		"Laterodorsal thalamic nucleus, dorsomedial part": [
			{
				"map": 0,
				"index": 228
			}
		],
		"Laterodorsal thalamic nucleus, ventrolateral part": [
			{
				"map": 0,
				"index": 229
			}
		],
		"Dorsal lateral geniculate nucleus": [
			{
				"map": 0,
				"index": 205
			}
		],
		"Medial geniculate body, ventral division": [
			{
				"map": 0,
				"index": 298
			}
		],
		"Medial geniculate body, dorsal division": [
			{
				"map": 0,
				"index": 295
			}
		],
		"Medial geniculate body, marginal zone": [
			{
				"map": 0,
				"index": 150
			}
		],
		"Medial geniculate body, medial division": [
			{
				"map": 0,
				"index": 297
			}
		],
		"Medial geniculate body, suprageniculate nucleus": [
			{
				"map": 0,
				"index": 299
			}
		],
		"Hypothalamic region, unspecified": [
			{
				"map": 0,
				"index": 48
			}
		],
		"Pretectal region": [
			{
				"map": 0,
				"index": 94
			}
		],
		"Nucleus sagulum": [
			{
				"map": 0,
				"index": 163
			}
		],
		"Inferior colliculus, dorsal cortex": [
			{
				"map": 0,
				"index": 142
			}
		],
		"Inferior colliculus, central nucleus": [
			{
				"map": 0,
				"index": 143
			}
		],
		"Inferior colliculus, external cortex": [
			{
				"map": 0,
				"index": 145
			}
		],
		"Superficial gray layer of the superior colliculus": [
			{
				"map": 0,
				"index": 50
			}
		],
		"Deeper layers of the superior colliculus": [
			{
				"map": 0,
				"index": 55
			}
		],
		"Substantia nigra, reticular part": [
			{
				"map": 0,
				"index": 187
			}
		],
		"Substantia nigra, compact part": [
			{
				"map": 0,
				"index": 188
			}
		],
		"Substantia nigra, lateral part": [
			{
				"map": 0,
				"index": 189
			}
		],
		"Ventral tegmental area": [
			{
				"map": 0,
				"index": 196
			}
		],
		"Peripeduncular nucleus": [
			{
				"map": 0,
				"index": 201
			}
		],
		"Interpeduncular nucleus": [
			{
				"map": 0,
				"index": 71
			}
		],
		"Periaqueductal gray": [
			{
				"map": 0,
				"index": 51
			}
		],
		"Brainstem, unspecified": [
			{
				"map": 0,
				"index": 47
			}
		],
		"Pontine nuclei": [
			{
				"map": 0,
				"index": 58
			}
		],
		"Molecular cell layer of the cerebellum": [
			{
				"map": 0,
				"index": 4
			}
		],
		"Cerebellum, unspecified": [
			{
				"map": 0,
				"index": 5
			}
		],
		"Ventral cochlear nucleus, anterior part": [
			{
				"map": 0,
				"index": 158
			}
		],
		"Ventral cochlear nucleus, posterior part": [
			{
				"map": 0,
				"index": 159
			}
		],
		"Ventral cochlear nucleus, cap area": [
			{
				"map": 0,
				"index": 160
			}
		],
		"Ventral cochlear nucleus, granule cell layer": [
			{
				"map": 0,
				"index": 123
			}
		],
		"Dorsal cochlear nucleus, molecular layer": [
			{
				"map": 0,
				"index": 126
			}
		],
		"Dorsal cochlear nucleus, fusiform and granule layer": [
			{
				"map": 0,
				"index": 127
			}
		],
		"Dorsal cochlear nucleus, deep core": [
			{
				"map": 0,
				"index": 128
			}
		],
		"Spinal trigeminal nucleus": [
			{
				"map": 0,
				"index": 75
			}
		],
		"Periventricular gray": [
			{
				"map": 0,
				"index": 56
			}
		],
		"Nucleus of the trapezoid body": [
			{
				"map": 0,
				"index": 131
			}
		],
		"Superior paraolivary nucleus": [
			{
				"map": 0,
				"index": 132
			}
		],
		"Medial superior olive": [
			{
				"map": 0,
				"index": 133
			}
		],
		"Lateral superior olive": [
			{
				"map": 0,
				"index": 134
			}
		],
		"Superior periolivary region": [
			{
				"map": 0,
				"index": 135
			}
		],
		"Ventral periolivary nuclei": [
			{
				"map": 0,
				"index": 136
			}
		],
		"Lateral lemniscus, ventral nucleus": [
			{
				"map": 0,
				"index": 137
			}
		],
		"Lateral lemniscus, intermediate nucleus": [
			{
				"map": 0,
				"index": 138
			}
		],
		"Lateral lemniscus, dorsal nucleus": [
			{
				"map": 0,
				"index": 139
			}
		],
		"Inferior olive": [
			{
				"map": 0,
				"index": 74
			}
		],
		"ventricular system, unspecified": [
			{
				"map": 0,
				"index": 33
			}
		],
		"4th ventricle": [
			{
				"map": 0,
				"index": 125
			}
		],
		"central canal": [
			{
				"map": 0,
				"index": 70
			}
		],
		"spinal cord": [
			{
				"map": 0,
				"index": 45
			}
		],
		"vestibular apparatus": [
			{
				"map": 0,
				"index": 119
			}
		],
		"cochlea": [
			{
				"map": 0,
				"index": 120
			}
		],
		"cochlear nerve": [
			{
				"map": 0,
				"index": 121
			}
		],
		"vestibular nerve": [
			{
				"map": 0,
				"index": 122
			}
		],
		"spiral ganglion": [
			{
				"map": 0,
				"index": 162
			}
		]
	},
	"volumes": [
		{
			"@type": "siibra/volume/v0.0.1",
			"detail": {
				"neuroglancer/precomputed": {
					"transform": [
						[
							1.0,
							0.0,
							0.0,
							-9550781.25
						],
						[
							0.0,
							1.0,
							0.0,
							-24355468.75
						],
						[
							0.0,
							0.0,
							1.0,
							-9707031.25
						],
						[
							0.0,
							0.0,
							0.0,
							1.0
						]
					]
				}
			},
			"urls": {
				"neuroglancer/precomputed": "https://neuroglancer.humanbrainproject.eu/precomputed/data-repo-ng-bot/20210927-waxholm-v4/precomputed/segmentations/WHS_SD_rat_atlas_v4"
			}
		}
	]
}
